{
"meta":{"test_sets":[],"test_metrics":[],"learn_metrics":[{"best_value":"Min","name":"MultiClass"}],"launch_mode":"Train","parameters":"","iteration_count":1000,"learn_sets":["learn"],"name":"experiment"},
"iterations":[
{"learn":[4.310701218],"iteration":0,"passed_time":0.7976860579,"remaining_time":796.8883719},
{"learn":[4.271678243],"iteration":1,"passed_time":0.8528800048,"remaining_time":425.5871224},
{"learn":[4.235049814],"iteration":2,"passed_time":0.9110707529,"remaining_time":302.7791802},
{"learn":[4.192146229],"iteration":3,"passed_time":0.9635396841,"remaining_time":239.9213813},
{"learn":[4.164623018],"iteration":4,"passed_time":0.9806717452,"remaining_time":195.1536773},
{"learn":[4.13420481],"iteration":5,"passed_time":1.036088547,"remaining_time":171.645336},
{"learn":[4.101209972],"iteration":6,"passed_time":1.092710646,"remaining_time":155.0088103},
{"learn":[4.070011944],"iteration":7,"passed_time":1.149036185,"remaining_time":142.4804869},
{"learn":[4.040701757],"iteration":8,"passed_time":1.209268117,"remaining_time":133.153856},
{"learn":[4.010379235],"iteration":9,"passed_time":1.266025312,"remaining_time":125.3365059},
{"learn":[3.983762853],"iteration":10,"passed_time":1.322975586,"remaining_time":118.9475323},
{"learn":[3.943691312],"iteration":11,"passed_time":1.376705868,"remaining_time":113.3487832},
{"learn":[3.912535721],"iteration":12,"passed_time":1.433060487,"remaining_time":108.8023616},
{"learn":[3.886419963],"iteration":13,"passed_time":1.489245269,"remaining_time":104.8854168},
{"learn":[3.85888735],"iteration":14,"passed_time":1.545467545,"remaining_time":101.4857022},
{"learn":[3.830094563],"iteration":15,"passed_time":1.599062375,"remaining_time":98.34233605},
{"learn":[3.805774995],"iteration":16,"passed_time":1.654451482,"remaining_time":95.66622395},
{"learn":[3.776236787],"iteration":17,"passed_time":1.710383288,"remaining_time":93.31091051},
{"learn":[3.751377142],"iteration":18,"passed_time":1.771289507,"remaining_time":91.45447402},
{"learn":[3.728529959],"iteration":19,"passed_time":1.826565469,"remaining_time":89.50170798},
{"learn":[3.703452254],"iteration":20,"passed_time":1.882688614,"remaining_time":87.76915015},
{"learn":[3.678278785],"iteration":21,"passed_time":1.944335328,"remaining_time":86.43454321},
{"learn":[3.648175132],"iteration":22,"passed_time":1.979374518,"remaining_time":84.08038715},
{"learn":[3.623168039],"iteration":23,"passed_time":2.034239826,"remaining_time":82.72575292},
{"learn":[3.598344405],"iteration":24,"passed_time":2.089295867,"remaining_time":81.4825388},
{"learn":[3.570748691],"iteration":25,"passed_time":2.143448018,"remaining_time":80.29686037},
{"learn":[3.549009965],"iteration":26,"passed_time":2.195828643,"remaining_time":79.13115814},
{"learn":[3.522177823],"iteration":27,"passed_time":2.248233382,"remaining_time":78.04581597},
{"learn":[3.499523859],"iteration":28,"passed_time":2.310588675,"remaining_time":77.36488289},
{"learn":[3.476532137],"iteration":29,"passed_time":2.366612354,"remaining_time":76.52046612},
{"learn":[3.454451806],"iteration":30,"passed_time":2.427477993,"remaining_time":75.87826373},
{"learn":[3.433329204],"iteration":31,"passed_time":2.480442359,"remaining_time":75.03338135},
{"learn":[3.413833698],"iteration":32,"passed_time":2.538704057,"remaining_time":74.39172192},
{"learn":[3.388191411],"iteration":33,"passed_time":2.603816803,"remaining_time":73.97903036},
{"learn":[3.365035632],"iteration":34,"passed_time":2.680534663,"remaining_time":73.90616999},
{"learn":[3.344100943],"iteration":35,"passed_time":2.734020597,"remaining_time":73.21099598},
{"learn":[3.324475037],"iteration":36,"passed_time":2.799999378,"remaining_time":72.87565949},
{"learn":[3.304363782],"iteration":37,"passed_time":2.869004977,"remaining_time":72.63112599},
{"learn":[3.284026431],"iteration":38,"passed_time":2.942018748,"remaining_time":72.49435941},
{"learn":[3.262499353],"iteration":39,"passed_time":3.004753785,"remaining_time":72.11409083},
{"learn":[3.242944066],"iteration":40,"passed_time":3.06541342,"remaining_time":71.70076755},
{"learn":[3.224974822],"iteration":41,"passed_time":3.141649722,"remaining_time":71.65953413},
{"learn":[3.208656286],"iteration":42,"passed_time":3.208017492,"remaining_time":71.39704046},
{"learn":[3.192692703],"iteration":43,"passed_time":3.273406275,"remaining_time":71.12219089},
{"learn":[3.175093461],"iteration":44,"passed_time":3.331726269,"remaining_time":70.70663526},
{"learn":[3.15762192],"iteration":45,"passed_time":3.391781856,"remaining_time":70.34260632},
{"learn":[3.141765835],"iteration":46,"passed_time":3.465614589,"remaining_time":70.27086603},
{"learn":[3.124491427],"iteration":47,"passed_time":3.529108804,"remaining_time":69.99399128},
{"learn":[3.107937085],"iteration":48,"passed_time":3.604780461,"remaining_time":69.96216772},
{"learn":[3.09299829],"iteration":49,"passed_time":3.679082917,"remaining_time":69.90257543},
{"learn":[3.076967343],"iteration":50,"passed_time":3.734263006,"remaining_time":69.48658024},
{"learn":[3.059656198],"iteration":51,"passed_time":3.788361051,"remaining_time":69.06473609},
{"learn":[3.044288241],"iteration":52,"passed_time":3.842790946,"remaining_time":68.6626986},
{"learn":[3.028592875],"iteration":53,"passed_time":3.894235194,"remaining_time":68.22123137},
{"learn":[3.01215525],"iteration":54,"passed_time":3.944752563,"remaining_time":67.77802132},
{"learn":[2.996646777],"iteration":55,"passed_time":4.004186777,"remaining_time":67.49914853},
{"learn":[2.980476376],"iteration":56,"passed_time":4.059085338,"remaining_time":67.15293814},
{"learn":[2.965399118],"iteration":57,"passed_time":4.115927274,"remaining_time":66.84833607},
{"learn":[2.95181213],"iteration":58,"passed_time":4.172920651,"remaining_time":66.55454801},
{"learn":[2.934817318],"iteration":59,"passed_time":4.236239408,"remaining_time":66.36775073},
{"learn":[2.920563549],"iteration":60,"passed_time":4.288873391,"remaining_time":66.02052646},
{"learn":[2.904326836],"iteration":61,"passed_time":4.345036057,"remaining_time":65.73619067},
{"learn":[2.890047486],"iteration":62,"passed_time":4.400420416,"remaining_time":65.4475227},
{"learn":[2.874487546],"iteration":63,"passed_time":4.457650773,"remaining_time":65.19314255},
{"learn":[2.859120264],"iteration":64,"passed_time":4.516442598,"remaining_time":64.96728968},
{"learn":[2.846059933],"iteration":65,"passed_time":4.579137436,"remaining_time":64.80173281},
{"learn":[2.83069469],"iteration":66,"passed_time":4.642146537,"remaining_time":64.64362267},
{"learn":[2.814245717],"iteration":67,"passed_time":4.706982289,"remaining_time":64.51334548},
{"learn":[2.80250542],"iteration":68,"passed_time":4.759632179,"remaining_time":64.22054433},
{"learn":[2.791144771],"iteration":69,"passed_time":4.815551694,"remaining_time":63.97804394},
{"learn":[2.775646035],"iteration":70,"passed_time":4.876227618,"remaining_time":63.8030346},
{"learn":[2.759654054],"iteration":71,"passed_time":4.930133319,"remaining_time":63.54394056},
{"learn":[2.744946786],"iteration":72,"passed_time":4.984743462,"remaining_time":63.29941356},
{"learn":[2.731152582],"iteration":73,"passed_time":5.037529432,"remaining_time":63.03719262},
{"learn":[2.717667865],"iteration":74,"passed_time":5.090654819,"remaining_time":62.78474276},
{"learn":[2.701215641],"iteration":75,"passed_time":5.14607283,"remaining_time":62.56541178},
{"learn":[2.686221508],"iteration":76,"passed_time":5.19993404,"remaining_time":62.33167687},
{"learn":[2.673079604],"iteration":77,"passed_time":5.257770563,"remaining_time":62.14954435},
{"learn":[2.661876718],"iteration":78,"passed_time":5.313969212,"remaining_time":61.95146385},
{"learn":[2.648786889],"iteration":79,"passed_time":5.370212308,"remaining_time":61.75744154},
{"learn":[2.63630892],"iteration":80,"passed_time":5.425567927,"remaining_time":61.55675216},
{"learn":[2.625457239],"iteration":81,"passed_time":5.480318942,"remaining_time":61.35283889},
{"learn":[2.615186819],"iteration":82,"passed_time":5.534004931,"remaining_time":61.14075328},
{"learn":[2.602825663],"iteration":83,"passed_time":5.589387603,"remaining_time":60.95094101},
{"learn":[2.591600837],"iteration":84,"passed_time":5.645791761,"remaining_time":60.77528778},
{"learn":[2.581918573],"iteration":85,"passed_time":5.702541047,"remaining_time":60.60607578},
{"learn":[2.56878178],"iteration":86,"passed_time":5.757821633,"remaining_time":60.42403622},
{"learn":[2.55676689],"iteration":87,"passed_time":5.81241271,"remaining_time":60.23773172},
{"learn":[2.54435027],"iteration":88,"passed_time":5.865990915,"remaining_time":60.04401936},
{"learn":[2.534332168],"iteration":89,"passed_time":5.925597765,"remaining_time":59.9143774},
{"learn":[2.522927237],"iteration":90,"passed_time":5.97857969,"remaining_time":59.72009822},
{"learn":[2.513421343],"iteration":91,"passed_time":6.033222254,"remaining_time":59.54528051},
{"learn":[2.50747916],"iteration":92,"passed_time":6.083467821,"remaining_time":59.33016466},
{"learn":[2.496456018],"iteration":93,"passed_time":6.145241975,"remaining_time":59.22967266},
{"learn":[2.487413649],"iteration":94,"passed_time":6.201087064,"remaining_time":59.07351361},
{"learn":[2.474294229],"iteration":95,"passed_time":6.257155236,"remaining_time":58.92154514},
{"learn":[2.464026018],"iteration":96,"passed_time":6.309373849,"remaining_time":58.73571737},
{"learn":[2.453838245],"iteration":97,"passed_time":6.363801998,"remaining_time":58.57295308},
{"learn":[2.442509387],"iteration":98,"passed_time":6.416808905,"remaining_time":58.39944266},
{"learn":[2.432212948],"iteration":99,"passed_time":6.471483005,"remaining_time":58.24334704},
{"learn":[2.422973313],"iteration":100,"passed_time":6.523515649,"remaining_time":58.0657482},
{"learn":[2.413721468],"iteration":101,"passed_time":6.575033732,"remaining_time":57.88608129},
{"learn":[2.403490551],"iteration":102,"passed_time":6.626579693,"remaining_time":57.70914548},
{"learn":[2.394217566],"iteration":103,"passed_time":6.680479093,"remaining_time":57.5548968},
{"learn":[2.383787887],"iteration":104,"passed_time":6.731712821,"remaining_time":57.37983785},
{"learn":[2.37351688],"iteration":105,"passed_time":6.786274642,"remaining_time":57.23518425},
{"learn":[2.363932601],"iteration":106,"passed_time":6.838120943,"remaining_time":57.06955142},
{"learn":[2.355332269],"iteration":107,"passed_time":6.892941739,"remaining_time":56.93059288},
{"learn":[2.34380179],"iteration":108,"passed_time":6.945647207,"remaining_time":56.7758868},
{"learn":[2.333186072],"iteration":109,"passed_time":7.002754226,"remaining_time":56.65864783},
{"learn":[2.32667707],"iteration":110,"passed_time":7.054269471,"remaining_time":56.49770775},
{"learn":[2.316917866],"iteration":111,"passed_time":7.111173708,"remaining_time":56.38144868},
{"learn":[2.309071761],"iteration":112,"passed_time":7.171975257,"remaining_time":56.29683232},
{"learn":[2.299505799],"iteration":113,"passed_time":7.227870953,"remaining_time":56.17450582},
{"learn":[2.290640788],"iteration":114,"passed_time":7.279878732,"remaining_time":56.02341459},
{"learn":[2.284496208],"iteration":115,"passed_time":7.332717799,"remaining_time":55.88036668},
{"learn":[2.276322242],"iteration":116,"passed_time":7.383459782,"remaining_time":55.72303408},
{"learn":[2.269678148],"iteration":117,"passed_time":7.435745328,"remaining_time":55.57904559},
{"learn":[2.259879445],"iteration":118,"passed_time":7.491852584,"remaining_time":55.46489182},
{"learn":[2.252995844],"iteration":119,"passed_time":7.545194275,"remaining_time":55.33142468},
{"learn":[2.245774361],"iteration":120,"passed_time":7.599287097,"remaining_time":55.2047385},
{"learn":[2.238381326],"iteration":121,"passed_time":7.658537624,"remaining_time":55.11636093},
{"learn":[2.230678816],"iteration":122,"passed_time":7.710205455,"remaining_time":54.97439174},
{"learn":[2.223077064],"iteration":123,"passed_time":7.762787566,"remaining_time":54.84033797},
{"learn":[2.215766183],"iteration":124,"passed_time":7.815213709,"remaining_time":54.70649596},
{"learn":[2.209431011],"iteration":125,"passed_time":7.868682191,"remaining_time":54.58117647},
{"learn":[2.201111386],"iteration":126,"passed_time":7.923091522,"remaining_time":54.4634559},
{"learn":[2.191603067],"iteration":127,"passed_time":7.977403511,"remaining_time":54.34606142},
{"learn":[2.182453687],"iteration":128,"passed_time":8.036028189,"remaining_time":54.25876397},
{"learn":[2.173027571],"iteration":129,"passed_time":8.088211113,"remaining_time":54.12879745},
{"learn":[2.167033782],"iteration":130,"passed_time":8.142294359,"remaining_time":54.01262441},
{"learn":[2.158854999],"iteration":131,"passed_time":8.192979864,"remaining_time":53.87504941},
{"learn":[2.150398749],"iteration":132,"passed_time":8.247590638,"remaining_time":53.76436905},
{"learn":[2.145818913],"iteration":133,"passed_time":8.297797299,"remaining_time":53.62606314},
{"learn":[2.138267526],"iteration":134,"passed_time":8.350125382,"remaining_time":53.50265522},
{"learn":[2.128932449],"iteration":135,"passed_time":8.405365853,"remaining_time":53.39879483},
{"learn":[2.124300218],"iteration":136,"passed_time":8.456676046,"remaining_time":53.27088633},
{"learn":[2.116294097],"iteration":137,"passed_time":8.50679314,"remaining_time":53.13663541},
{"learn":[2.110907494],"iteration":138,"passed_time":8.558665152,"remaining_time":53.01446544},
{"learn":[2.10377276],"iteration":139,"passed_time":8.613224141,"remaining_time":52.90980544},
{"learn":[2.098067853],"iteration":140,"passed_time":8.666367273,"remaining_time":52.79723041},
{"learn":[2.090406253],"iteration":141,"passed_time":8.719199967,"remaining_time":52.6836167},
{"learn":[2.082168305],"iteration":142,"passed_time":8.771478248,"remaining_time":52.56753048},
{"learn":[2.073891773],"iteration":143,"passed_time":8.822808089,"remaining_time":52.44669253},
{"learn":[2.06630637],"iteration":144,"passed_time":8.875972547,"remaining_time":52.33763123},
{"learn":[2.060851333],"iteration":145,"passed_time":8.929394429,"remaining_time":52.23084138},
{"learn":[2.054956043],"iteration":146,"passed_time":8.981355857,"remaining_time":52.11630304},
{"learn":[2.047170705],"iteration":147,"passed_time":9.034033663,"remaining_time":52.00673433},
{"learn":[2.040974585],"iteration":148,"passed_time":9.087142746,"remaining_time":51.90039246},
{"learn":[2.033170434],"iteration":149,"passed_time":9.140512101,"remaining_time":51.79623524},
{"learn":[2.027253932],"iteration":150,"passed_time":9.191492409,"remaining_time":51.67931824},
{"learn":[2.021761838],"iteration":151,"passed_time":9.24425629,"remaining_time":51.5732193},
{"learn":[2.014463007],"iteration":152,"passed_time":9.298119869,"remaining_time":51.47390542},
{"learn":[2.008166042],"iteration":153,"passed_time":9.347668462,"remaining_time":51.35147739},
{"learn":[2.000360288],"iteration":154,"passed_time":9.400639618,"remaining_time":51.24864824},
{"learn":[1.994054117],"iteration":155,"passed_time":9.451739269,"remaining_time":51.13633297},
{"learn":[1.988616635],"iteration":156,"passed_time":9.504086281,"remaining_time":51.03149512},
{"learn":[1.981240343],"iteration":157,"passed_time":9.558411809,"remaining_time":50.93786546},
{"learn":[1.973774007],"iteration":158,"passed_time":9.608917936,"remaining_time":50.8245282},
{"learn":[1.966124581],"iteration":159,"passed_time":9.662958061,"remaining_time":50.73052982},
{"learn":[1.961894859],"iteration":160,"passed_time":9.713997803,"remaining_time":50.62139228},
{"learn":[1.956895043],"iteration":161,"passed_time":9.765284568,"remaining_time":50.5142498},
{"learn":[1.950552655],"iteration":162,"passed_time":9.816592161,"remaining_time":50.40789963},
{"learn":[1.944022602],"iteration":163,"passed_time":9.872793827,"remaining_time":50.32716853},
{"learn":[1.937998492],"iteration":164,"passed_time":9.927239018,"remaining_time":50.23784594},
{"learn":[1.930279255],"iteration":165,"passed_time":9.97881573,"remaining_time":50.13453204},
{"learn":[1.923122643],"iteration":166,"passed_time":10.03140418,"remaining_time":50.03688433},
{"learn":[1.918945997],"iteration":167,"passed_time":10.08121274,"remaining_time":49.92600593},
{"learn":[1.912567421],"iteration":168,"passed_time":10.13501887,"remaining_time":49.835507},
{"learn":[1.905971661],"iteration":169,"passed_time":10.19214562,"remaining_time":49.76165214},
{"learn":[1.898617608],"iteration":170,"passed_time":10.2453388,"remaining_time":49.66892319},
{"learn":[1.895996753],"iteration":171,"passed_time":10.29591347,"remaining_time":49.56404855},
{"learn":[1.889314103],"iteration":172,"passed_time":10.34862638,"remaining_time":49.47002322},
{"learn":[1.883963562],"iteration":173,"passed_time":10.40718143,"remaining_time":49.4042061},
{"learn":[1.879230947],"iteration":174,"passed_time":10.45921396,"remaining_time":49.30772294},
{"learn":[1.874301183],"iteration":175,"passed_time":10.5127296,"remaining_time":49.21868857},
{"learn":[1.869565208],"iteration":176,"passed_time":10.56401999,"remaining_time":49.11970876},
{"learn":[1.862882346],"iteration":177,"passed_time":10.61745908,"remaining_time":49.03118744},
{"learn":[1.858065913],"iteration":178,"passed_time":10.67024269,"remaining_time":48.94005167},
{"learn":[1.852966681],"iteration":179,"passed_time":10.72069229,"remaining_time":48.83870933},
{"learn":[1.846804576],"iteration":180,"passed_time":10.7712053,"remaining_time":48.73821624},
{"learn":[1.840730261],"iteration":181,"passed_time":10.82533498,"remaining_time":48.65452753},
{"learn":[1.836305309],"iteration":182,"passed_time":10.87732123,"remaining_time":48.56159261},
{"learn":[1.829963732],"iteration":183,"passed_time":10.93126208,"remaining_time":48.47777094},
{"learn":[1.824858745],"iteration":184,"passed_time":10.98340059,"remaining_time":48.38633234},
{"learn":[1.818948708],"iteration":185,"passed_time":11.03695458,"remaining_time":48.30151089},
{"learn":[1.812588465],"iteration":186,"passed_time":11.08914562,"remaining_time":48.21109833},
{"learn":[1.807524934],"iteration":187,"passed_time":11.14055055,"remaining_time":48.11769704},
{"learn":[1.803161862],"iteration":188,"passed_time":11.19780399,"remaining_time":48.04983616},
{"learn":[1.797026162],"iteration":189,"passed_time":11.25149673,"remaining_time":47.96690713},
{"learn":[1.793007744],"iteration":190,"passed_time":11.3030283,"remaining_time":47.87513032},
{"learn":[1.788381771],"iteration":191,"passed_time":11.35716594,"remaining_time":47.79474001},
{"learn":[1.782402939],"iteration":192,"passed_time":11.4125336,"remaining_time":47.71976487},
{"learn":[1.777054369],"iteration":193,"passed_time":11.46504806,"remaining_time":47.63313783},
{"learn":[1.771190234],"iteration":194,"passed_time":11.52222661,"remaining_time":47.56611499},
{"learn":[1.765890876],"iteration":195,"passed_time":11.57523423,"remaining_time":47.48208327},
{"learn":[1.760691257],"iteration":196,"passed_time":11.62617354,"remaining_time":47.38993581},
{"learn":[1.75476433],"iteration":197,"passed_time":11.68081256,"remaining_time":47.31319028},
{"learn":[1.749153663],"iteration":198,"passed_time":11.73253434,"remaining_time":47.22492464},
{"learn":[1.744718767],"iteration":199,"passed_time":11.7844915,"remaining_time":47.13796602},
{"learn":[1.739440042],"iteration":200,"passed_time":11.84231337,"remaining_time":47.07466857},
{"learn":[1.735043201],"iteration":201,"passed_time":11.89537967,"remaining_time":46.9926385},
{"learn":[1.729324357],"iteration":202,"passed_time":11.95391966,"remaining_time":46.93238407},
{"learn":[1.725523692],"iteration":203,"passed_time":12.00496326,"remaining_time":46.84289585},
{"learn":[1.720095873],"iteration":204,"passed_time":12.05619025,"remaining_time":46.75449388},
{"learn":[1.715100388],"iteration":205,"passed_time":12.10980146,"remaining_time":46.67564253},
{"learn":[1.709989807],"iteration":206,"passed_time":12.16385172,"remaining_time":46.59871698},
{"learn":[1.704162858],"iteration":207,"passed_time":12.21860866,"remaining_time":46.5247022},
{"learn":[1.699094652],"iteration":208,"passed_time":12.26933523,"remaining_time":46.43561801},
{"learn":[1.696658521],"iteration":209,"passed_time":12.31971008,"remaining_time":46.345576},
{"learn":[1.690818512],"iteration":210,"passed_time":12.37297069,"remaining_time":46.26670085},
{"learn":[1.685355141],"iteration":211,"passed_time":12.42995011,"remaining_time":46.20189004},
{"learn":[1.680783071],"iteration":212,"passed_time":12.4787006,"remaining_time":46.10674823},
{"learn":[1.676111564],"iteration":213,"passed_time":12.53080094,"remaining_time":46.02434363},
{"learn":[1.669691296],"iteration":214,"passed_time":12.58687346,"remaining_time":45.95672404},
{"learn":[1.66462235],"iteration":215,"passed_time":12.63845639,"remaining_time":45.8729158},
{"learn":[1.659927412],"iteration":216,"passed_time":12.68990462,"remaining_time":45.78891853},
{"learn":[1.653523132],"iteration":217,"passed_time":12.74607218,"remaining_time":45.72214885},
{"learn":[1.650135611],"iteration":218,"passed_time":12.79560769,"remaining_time":45.63182469},
{"learn":[1.643481611],"iteration":219,"passed_time":12.8513383,"remaining_time":45.56383579},
{"learn":[1.639659536],"iteration":220,"passed_time":12.90244778,"remaining_time":45.47966888},
{"learn":[1.635709845],"iteration":221,"passed_time":12.96304684,"remaining_time":45.42905606},
{"learn":[1.630172174],"iteration":222,"passed_time":13.01776919,"remaining_time":45.35787741},
{"learn":[1.625722189],"iteration":223,"passed_time":13.06901192,"remaining_time":45.2747913},
{"learn":[1.621629168],"iteration":224,"passed_time":13.12152532,"remaining_time":45.196365},
{"learn":[1.616461211],"iteration":225,"passed_time":13.17364857,"remaining_time":45.11683183},
{"learn":[1.612785851],"iteration":226,"passed_time":13.22494581,"remaining_time":45.03472735},
{"learn":[1.607677683],"iteration":227,"passed_time":13.27967761,"remaining_time":44.96452243},
{"learn":[1.604645621],"iteration":228,"passed_time":13.33233569,"remaining_time":44.88747083},
{"learn":[1.600892242],"iteration":229,"passed_time":13.38362825,"remaining_time":44.80605979},
{"learn":[1.595965748],"iteration":230,"passed_time":13.43638667,"remaining_time":44.7297894},
{"learn":[1.59226137],"iteration":231,"passed_time":13.48453586,"remaining_time":44.63846353},
{"learn":[1.589151946],"iteration":232,"passed_time":13.53461931,"remaining_time":44.55387557},
{"learn":[1.58371579],"iteration":233,"passed_time":13.58776652,"remaining_time":44.47961178},
{"learn":[1.578512178],"iteration":234,"passed_time":13.64108397,"remaining_time":44.40608186},
{"learn":[1.573019558],"iteration":235,"passed_time":13.69460712,"remaining_time":44.33338917},
{"learn":[1.567711248],"iteration":236,"passed_time":13.74735411,"remaining_time":44.25835944},
{"learn":[1.563893953],"iteration":237,"passed_time":13.7985212,"remaining_time":44.17845863},
{"learn":[1.559986027],"iteration":238,"passed_time":13.85164392,"remaining_time":44.10502519},
{"learn":[1.555025835],"iteration":239,"passed_time":13.90647586,"remaining_time":44.03717357},
{"learn":[1.551502828],"iteration":240,"passed_time":13.9612642,"remaining_time":43.96929266},
{"learn":[1.545614125],"iteration":241,"passed_time":14.01607212,"remaining_time":43.90158127},
{"learn":[1.542417103],"iteration":242,"passed_time":14.06630692,"remaining_time":43.81972979},
{"learn":[1.538368248],"iteration":243,"passed_time":14.11721605,"remaining_time":43.74022679},
{"learn":[1.532812344],"iteration":244,"passed_time":14.18013511,"remaining_time":43.69796737},
{"learn":[1.528487599],"iteration":245,"passed_time":14.23149239,"remaining_time":43.62010268},
{"learn":[1.525459358],"iteration":246,"passed_time":14.28174773,"remaining_time":43.53909328},
{"learn":[1.521028881],"iteration":247,"passed_time":14.33486063,"remaining_time":43.46699676},
{"learn":[1.517092523],"iteration":248,"passed_time":14.38941104,"remaining_time":43.39938832},
{"learn":[1.513615421],"iteration":249,"passed_time":14.44020522,"remaining_time":43.32061565},
{"learn":[1.509681035],"iteration":250,"passed_time":14.49226513,"remaining_time":43.24584296},
{"learn":[1.505052406],"iteration":251,"passed_time":14.54530941,"remaining_time":43.17417237},
{"learn":[1.500929427],"iteration":252,"passed_time":14.59684596,"remaining_time":43.09819737},
{"learn":[1.496130808],"iteration":253,"passed_time":14.65028797,"remaining_time":43.02801112},
{"learn":[1.492347981],"iteration":254,"passed_time":14.70308243,"remaining_time":42.95606436},
{"learn":[1.49018768],"iteration":255,"passed_time":14.75339503,"remaining_time":42.87705432},
{"learn":[1.486197557],"iteration":256,"passed_time":14.80761091,"remaining_time":42.80955217},
{"learn":[1.484293494],"iteration":257,"passed_time":14.85950259,"remaining_time":42.7354687},
{"learn":[1.479746052],"iteration":258,"passed_time":14.9137988,"remaining_time":42.66843595},
{"learn":[1.47789774],"iteration":259,"passed_time":14.96851736,"remaining_time":42.60270326},
{"learn":[1.472844164],"iteration":260,"passed_time":15.02472605,"remaining_time":42.54127414},
{"learn":[1.46851192],"iteration":261,"passed_time":15.07961079,"remaining_time":42.47615558},
{"learn":[1.465126423],"iteration":262,"passed_time":15.13141994,"remaining_time":42.40249619},
{"learn":[1.46277784],"iteration":263,"passed_time":15.18357071,"remaining_time":42.3299547},
{"learn":[1.459525033],"iteration":264,"passed_time":15.23501848,"remaining_time":42.2556173},
{"learn":[1.456921199],"iteration":265,"passed_time":15.28626618,"remaining_time":42.18089992},
{"learn":[1.453471615],"iteration":266,"passed_time":15.33554672,"remaining_time":42.10095785},
{"learn":[1.451789871],"iteration":267,"passed_time":15.3860896,"remaining_time":42.0246925},
{"learn":[1.448731479],"iteration":268,"passed_time":15.4377471,"remaining_time":41.95164733},
{"learn":[1.445753209],"iteration":269,"passed_time":15.49010435,"remaining_time":41.8806525},
{"learn":[1.442790687],"iteration":270,"passed_time":15.54309128,"remaining_time":41.81148909},
{"learn":[1.44157875],"iteration":271,"passed_time":15.59273337,"remaining_time":41.73349224},
{"learn":[1.438783251],"iteration":272,"passed_time":15.64807848,"remaining_time":41.67089031},
{"learn":[1.435444952],"iteration":273,"passed_time":15.69919079,"remaining_time":41.59712596},
{"learn":[1.432267643],"iteration":274,"passed_time":15.75095076,"remaining_time":41.52523382},
{"learn":[1.428593019],"iteration":275,"passed_time":15.80212103,"remaining_time":41.45194066},
{"learn":[1.42405302],"iteration":276,"passed_time":15.85476758,"remaining_time":41.3826605},
{"learn":[1.421257458],"iteration":277,"passed_time":15.90673017,"remaining_time":41.31172367},
{"learn":[1.418101815],"iteration":278,"passed_time":15.96007601,"remaining_time":41.24449749},
{"learn":[1.41543625],"iteration":279,"passed_time":16.0110542,"remaining_time":41.17128224},
{"learn":[1.411288053],"iteration":280,"passed_time":16.06601703,"remaining_time":41.1084208},
{"learn":[1.408032174],"iteration":281,"passed_time":16.11755092,"remaining_time":41.03688496},
{"learn":[1.403837768],"iteration":282,"passed_time":16.16833012,"remaining_time":40.96357844},
{"learn":[1.400051567],"iteration":283,"passed_time":16.22369164,"remaining_time":40.90198316},
{"learn":[1.395676654],"iteration":284,"passed_time":16.27673047,"remaining_time":40.83460452},
{"learn":[1.391644452],"iteration":285,"passed_time":16.32789375,"remaining_time":40.76264385},
{"learn":[1.387368605],"iteration":286,"passed_time":16.38132737,"remaining_time":40.69646835},
{"learn":[1.38505346],"iteration":287,"passed_time":16.431602,"remaining_time":40.6225716},
{"learn":[1.381608293],"iteration":288,"passed_time":16.48315121,"remaining_time":40.55197408},
{"learn":[1.380146696],"iteration":289,"passed_time":16.53396834,"remaining_time":40.47971559},
{"learn":[1.375296557],"iteration":290,"passed_time":16.58716081,"remaining_time":40.41339181},
{"learn":[1.37037556],"iteration":291,"passed_time":16.64480068,"remaining_time":40.35794138},
{"learn":[1.365762997],"iteration":292,"passed_time":16.69847077,"remaining_time":40.29289706},
{"learn":[1.361301172],"iteration":293,"passed_time":16.74994,"remaining_time":40.22264504},
{"learn":[1.357629474],"iteration":294,"passed_time":16.80314124,"remaining_time":40.15665958},
{"learn":[1.355312786],"iteration":295,"passed_time":16.85479437,"remaining_time":40.0870785},
{"learn":[1.352315127],"iteration":296,"passed_time":16.90574117,"remaining_time":40.01594627},
{"learn":[1.349859814],"iteration":297,"passed_time":16.9614386,"remaining_time":39.9561406},
{"learn":[1.345295213],"iteration":298,"passed_time":17.01650349,"remaining_time":39.89487941},
{"learn":[1.341203535],"iteration":299,"passed_time":17.06977403,"remaining_time":39.82947273},
{"learn":[1.339154795],"iteration":300,"passed_time":17.12016955,"remaining_time":39.75747015},
{"learn":[1.336001337],"iteration":301,"passed_time":17.17222387,"remaining_time":39.68944456},
{"learn":[1.333181256],"iteration":302,"passed_time":17.22440072,"remaining_time":39.62180627},
{"learn":[1.330658027],"iteration":303,"passed_time":17.27548034,"remaining_time":39.55175761},
{"learn":[1.329149167],"iteration":304,"passed_time":17.3279438,"remaining_time":39.48498669},
{"learn":[1.325577387],"iteration":305,"passed_time":17.38121725,"remaining_time":39.42014631},
{"learn":[1.321290038],"iteration":306,"passed_time":17.43469872,"remaining_time":39.35585087},
{"learn":[1.318767953],"iteration":307,"passed_time":17.48630901,"remaining_time":39.28742155},
{"learn":[1.31677281],"iteration":308,"passed_time":17.53802695,"remaining_time":39.21934183},
{"learn":[1.314341556],"iteration":309,"passed_time":17.59079556,"remaining_time":39.15370625},
{"learn":[1.312109829],"iteration":310,"passed_time":17.6456388,"remaining_time":39.09274961},
{"learn":[1.309704541],"iteration":311,"passed_time":17.69566506,"remaining_time":39.02121013},
{"learn":[1.307599906],"iteration":312,"passed_time":17.7454844,"remaining_time":38.94935394},
{"learn":[1.304869206],"iteration":313,"passed_time":17.79784104,"remaining_time":38.88318138},
{"learn":[1.302976742],"iteration":314,"passed_time":17.84874052,"remaining_time":38.8139278},
{"learn":[1.299881802],"iteration":315,"passed_time":17.9029539,"remaining_time":38.7519635},
{"learn":[1.295653321],"iteration":316,"passed_time":17.95612437,"remaining_time":38.68780109},
{"learn":[1.292897327],"iteration":317,"passed_time":18.00769651,"remaining_time":38.62027995},
{"learn":[1.291202725],"iteration":318,"passed_time":18.05751401,"remaining_time":38.54911298},
{"learn":[1.286813855],"iteration":319,"passed_time":18.11252139,"remaining_time":38.48910796},
{"learn":[1.283423351],"iteration":320,"passed_time":18.16374776,"remaining_time":38.42113622},
{"learn":[1.280513815],"iteration":321,"passed_time":18.29360103,"remaining_time":38.51882454},
{"learn":[1.276393079],"iteration":322,"passed_time":18.36072106,"remaining_time":38.48361659},
{"learn":[1.272725281],"iteration":323,"passed_time":18.41138932,"remaining_time":38.41388636},
{"learn":[1.271654988],"iteration":324,"passed_time":18.45928016,"remaining_time":38.33850494},
{"learn":[1.26816837],"iteration":325,"passed_time":18.50962072,"remaining_time":38.26835695},
{"learn":[1.263906498],"iteration":326,"passed_time":18.56325516,"remaining_time":38.20510925},
{"learn":[1.261309175],"iteration":327,"passed_time":18.61354677,"remaining_time":38.13507144},
{"learn":[1.258982296],"iteration":328,"passed_time":18.66652098,"remaining_time":38.07062485},
{"learn":[1.255874971],"iteration":329,"passed_time":18.71860772,"remaining_time":38.00444598},
{"learn":[1.252222705],"iteration":330,"passed_time":18.76862893,"remaining_time":37.93417751},
{"learn":[1.249945579],"iteration":331,"passed_time":18.82242519,"remaining_time":37.87162659},
{"learn":[1.247183886],"iteration":332,"passed_time":18.87130016,"remaining_time":37.7992709},
{"learn":[1.2436435],"iteration":333,"passed_time":18.92524448,"remaining_time":37.73716415},
{"learn":[1.239987052],"iteration":334,"passed_time":18.97836843,"remaining_time":37.67347763},
{"learn":[1.237596818],"iteration":335,"passed_time":19.02941181,"remaining_time":37.60574239},
{"learn":[1.235862325],"iteration":336,"passed_time":19.08078289,"remaining_time":37.53875091},
{"learn":[1.233527895],"iteration":337,"passed_time":19.1332079,"remaining_time":37.47391607},
{"learn":[1.229627118],"iteration":338,"passed_time":19.18487515,"remaining_time":37.40767691},
{"learn":[1.225822429],"iteration":339,"passed_time":19.23932644,"remaining_time":37.3469278},
{"learn":[1.222128813],"iteration":340,"passed_time":19.29112702,"remaining_time":37.28109299},
{"learn":[1.218991344],"iteration":341,"passed_time":19.34200055,"remaining_time":37.21355661},
{"learn":[1.215130793],"iteration":342,"passed_time":19.39788431,"remaining_time":37.15571427},
{"learn":[1.212850604],"iteration":343,"passed_time":19.44948234,"remaining_time":37.08971051},
{"learn":[1.209425193],"iteration":344,"passed_time":19.50101271,"remaining_time":37.0236618},
{"learn":[1.20575351],"iteration":345,"passed_time":19.57576314,"remaining_time":37.00158698},
{"learn":[1.202021607],"iteration":346,"passed_time":19.63578796,"remaining_time":36.95149724},
{"learn":[1.198730826],"iteration":347,"passed_time":19.69312091,"remaining_time":36.89630699},
{"learn":[1.194991425],"iteration":348,"passed_time":19.7509312,"remaining_time":36.84199488},
{"learn":[1.191474983],"iteration":349,"passed_time":19.80577736,"remaining_time":36.78215795},
{"learn":[1.188861805],"iteration":350,"passed_time":19.8657831,"remaining_time":36.73188954},
{"learn":[1.185956684],"iteration":351,"passed_time":19.91948578,"remaining_time":36.66996245},
{"learn":[1.18274934],"iteration":352,"passed_time":19.9778929,"remaining_time":36.61670454},
{"learn":[1.181503608],"iteration":353,"passed_time":20.03320354,"remaining_time":36.55776691},
{"learn":[1.178783145],"iteration":354,"passed_time":20.08834931,"remaining_time":36.49855015},
{"learn":[1.175159669],"iteration":355,"passed_time":20.14091215,"remaining_time":36.43468378},
{"learn":[1.171673182],"iteration":356,"passed_time":20.19600011,"remaining_time":36.37542877},
{"learn":[1.168279417],"iteration":357,"passed_time":20.25103283,"remaining_time":36.31609798},
{"learn":[1.165011702],"iteration":358,"passed_time":20.30394845,"remaining_time":36.25301102},
{"learn":[1.162871977],"iteration":359,"passed_time":20.35800503,"remaining_time":36.19200893},
{"learn":[1.160275017],"iteration":360,"passed_time":20.41149253,"remaining_time":36.13003803},
{"learn":[1.15755815],"iteration":361,"passed_time":20.46404254,"remaining_time":36.06646172},
{"learn":[1.154690076],"iteration":362,"passed_time":20.52091163,"remaining_time":36.01052536},
{"learn":[1.15146062],"iteration":363,"passed_time":20.57116411,"remaining_time":35.94302301},
{"learn":[1.149693791],"iteration":364,"passed_time":20.62537584,"remaining_time":35.88250317},
{"learn":[1.146628875],"iteration":365,"passed_time":20.67723489,"remaining_time":35.81794241},
{"learn":[1.144088456],"iteration":366,"passed_time":20.72873342,"remaining_time":35.75282903},
{"learn":[1.141090148],"iteration":367,"passed_time":20.78428811,"remaining_time":35.69475567},
{"learn":[1.139192839],"iteration":368,"passed_time":20.83635135,"remaining_time":35.63072548},
{"learn":[1.135492829],"iteration":369,"passed_time":20.89327312,"remaining_time":35.57503261},
{"learn":[1.132267113],"iteration":370,"passed_time":20.94651032,"remaining_time":35.51308623},
{"learn":[1.129879959],"iteration":371,"passed_time":20.99955215,"remaining_time":35.45085686},
{"learn":[1.12754457],"iteration":372,"passed_time":21.05376179,"remaining_time":35.39063979},
{"learn":[1.124495978],"iteration":373,"passed_time":21.10538859,"remaining_time":35.32613171},
{"learn":[1.121311829],"iteration":374,"passed_time":21.1590394,"remaining_time":35.26506566},
{"learn":[1.119156332],"iteration":375,"passed_time":21.21010664,"remaining_time":35.19975145},
{"learn":[1.117263408],"iteration":376,"passed_time":21.25897752,"remaining_time":35.13088327},
{"learn":[1.114449084],"iteration":377,"passed_time":21.31740089,"remaining_time":35.07783955},
{"learn":[1.113356598],"iteration":378,"passed_time":21.36526668,"remaining_time":35.00746862},
{"learn":[1.11078645],"iteration":379,"passed_time":21.41906627,"remaining_time":34.94689759},
{"learn":[1.107874489],"iteration":380,"passed_time":21.47239163,"remaining_time":34.88559165},
{"learn":[1.10428627],"iteration":381,"passed_time":21.52567536,"remaining_time":34.82426014},
{"learn":[1.100269806],"iteration":382,"passed_time":21.57918221,"remaining_time":34.76333009},
{"learn":[1.097648163],"iteration":383,"passed_time":21.63511881,"remaining_time":34.70633642},
{"learn":[1.094337372],"iteration":384,"passed_time":21.68644794,"remaining_time":34.64198827},
{"learn":[1.091938327],"iteration":385,"passed_time":21.74029916,"remaining_time":34.58171939},
{"learn":[1.088538098],"iteration":386,"passed_time":21.79264945,"remaining_time":34.51910623},
{"learn":[1.085681279],"iteration":387,"passed_time":21.84919088,"remaining_time":34.46315675},
{"learn":[1.082560514],"iteration":388,"passed_time":21.90229135,"remaining_time":34.40179953},
{"learn":[1.080285211],"iteration":389,"passed_time":21.95279094,"remaining_time":34.33641659},
{"learn":[1.076916471],"iteration":390,"passed_time":22.0064146,"remaining_time":34.27597569},
{"learn":[1.073500895],"iteration":391,"passed_time":22.05849457,"remaining_time":34.21317526},
{"learn":[1.07128802],"iteration":392,"passed_time":22.10863472,"remaining_time":34.14743327},
{"learn":[1.069154582],"iteration":393,"passed_time":22.16233695,"remaining_time":34.08724922},
{"learn":[1.065895904],"iteration":394,"passed_time":22.21587517,"remaining_time":34.02684678},
{"learn":[1.063871288],"iteration":395,"passed_time":22.27436932,"remaining_time":33.97403806},
{"learn":[1.061357023],"iteration":396,"passed_time":22.32630626,"remaining_time":33.911241},
{"learn":[1.058866212],"iteration":397,"passed_time":22.37818285,"remaining_time":33.84840723},
{"learn":[1.056451654],"iteration":398,"passed_time":22.43356708,"remaining_time":33.79091181},
{"learn":[1.054341833],"iteration":399,"passed_time":22.48505596,"remaining_time":33.72758395},
{"learn":[1.051947948],"iteration":400,"passed_time":22.53755861,"remaining_time":33.66582944},
{"learn":[1.049255528],"iteration":401,"passed_time":22.59301252,"remaining_time":33.60851117},
{"learn":[1.046049763],"iteration":402,"passed_time":22.64791292,"remaining_time":33.55038216},
{"learn":[1.044333765],"iteration":403,"passed_time":22.70010856,"remaining_time":33.48827896},
{"learn":[1.042729805],"iteration":404,"passed_time":22.75226305,"remaining_time":33.42616423},
{"learn":[1.03976144],"iteration":405,"passed_time":22.80565724,"remaining_time":33.36591232},
{"learn":[1.036552723],"iteration":406,"passed_time":22.86517376,"remaining_time":33.31461435},
{"learn":[1.033664104],"iteration":407,"passed_time":22.91928334,"remaining_time":33.25543073},
{"learn":[1.030474085],"iteration":408,"passed_time":22.97513564,"remaining_time":33.19879013},
{"learn":[1.027786649],"iteration":409,"passed_time":23.02754237,"remaining_time":33.13719512},
{"learn":[1.025627725],"iteration":410,"passed_time":23.07791327,"remaining_time":33.07272729},
{"learn":[1.022967566],"iteration":411,"passed_time":23.13385439,"remaining_time":33.01627762},
{"learn":[1.020668896],"iteration":412,"passed_time":23.18669112,"remaining_time":32.95541812},
{"learn":[1.018310689],"iteration":413,"passed_time":23.23947144,"remaining_time":32.89451755},
{"learn":[1.015557363],"iteration":414,"passed_time":23.29596762,"remaining_time":32.83889412},
{"learn":[1.012997054],"iteration":415,"passed_time":23.34882008,"remaining_time":32.77815126},
{"learn":[1.01020759],"iteration":416,"passed_time":23.40646893,"remaining_time":32.724152},
{"learn":[1.007910563],"iteration":417,"passed_time":23.46165193,"remaining_time":32.66670196},
{"learn":[1.005119198],"iteration":418,"passed_time":23.5149276,"remaining_time":32.60661799},
{"learn":[1.003181905],"iteration":419,"passed_time":23.57286799,"remaining_time":32.55300818},
{"learn":[1.001613181],"iteration":420,"passed_time":23.62292008,"remaining_time":32.48852903},
{"learn":[1.000096677],"iteration":421,"passed_time":23.68165673,"remaining_time":32.43601324},
{"learn":[0.9973669766],"iteration":422,"passed_time":23.73316993,"remaining_time":32.37361478},
{"learn":[0.9955446969],"iteration":423,"passed_time":23.78524746,"remaining_time":32.31203428},
{"learn":[0.9928081108],"iteration":424,"passed_time":23.84115588,"remaining_time":32.25568148},
{"learn":[0.990947685],"iteration":425,"passed_time":23.89290313,"remaining_time":32.19372393},
{"learn":[0.9885572411],"iteration":426,"passed_time":23.94547016,"remaining_time":32.13291429},
{"learn":[0.9859296627],"iteration":427,"passed_time":24.00090234,"remaining_time":32.07597228},
{"learn":[0.9830559445],"iteration":428,"passed_time":24.05250125,"remaining_time":32.01393523},
{"learn":[0.9809737407],"iteration":429,"passed_time":24.10715032,"remaining_time":31.95598996},
{"learn":[0.9788054755],"iteration":430,"passed_time":24.16016581,"remaining_time":31.89590335},
{"learn":[0.9764778879],"iteration":431,"passed_time":24.21348638,"remaining_time":31.83625061},
{"learn":[0.9737095611],"iteration":432,"passed_time":24.27761408,"remaining_time":31.79077871},
{"learn":[0.9719618722],"iteration":433,"passed_time":24.32925955,"remaining_time":31.72894218},
{"learn":[0.9692640757],"iteration":434,"passed_time":24.38564084,"remaining_time":31.67330361},
{"learn":[0.9669811936],"iteration":435,"passed_time":24.44137013,"remaining_time":31.61681824},
{"learn":[0.9650695165],"iteration":436,"passed_time":24.49121557,"remaining_time":31.55275599},
{"learn":[0.9635198001],"iteration":437,"passed_time":24.54459226,"remaining_time":31.49328962},
{"learn":[0.9616578282],"iteration":438,"passed_time":24.59668812,"remaining_time":31.4322142},
{"learn":[0.9588710405],"iteration":439,"passed_time":24.64793729,"remaining_time":31.37010201},
{"learn":[0.9564895105],"iteration":440,"passed_time":24.70138431,"remaining_time":31.31082501},
{"learn":[0.9538780156],"iteration":441,"passed_time":24.75773257,"remaining_time":31.25523705},
{"learn":[0.9521988911],"iteration":442,"passed_time":24.81015907,"remaining_time":31.19471468},
{"learn":[0.9512854255],"iteration":443,"passed_time":24.86336788,"remaining_time":31.13520842},
{"learn":[0.9492101266],"iteration":444,"passed_time":24.91785423,"remaining_time":31.07732381},
{"learn":[0.9463794416],"iteration":445,"passed_time":24.97087359,"remaining_time":31.01763221},
{"learn":[0.9435684202],"iteration":446,"passed_time":25.02696544,"remaining_time":30.96177157},
{"learn":[0.9421600299],"iteration":447,"passed_time":25.07610886,"remaining_time":30.89734841},
{"learn":[0.9401838011],"iteration":448,"passed_time":25.13130606,"remaining_time":30.84042236},
{"learn":[0.9384474308],"iteration":449,"passed_time":25.18745212,"remaining_time":30.78466371},
{"learn":[0.937488563],"iteration":450,"passed_time":25.23724054,"remaining_time":30.7211642},
{"learn":[0.9355015865],"iteration":451,"passed_time":25.29272845,"remaining_time":30.66463538},
{"learn":[0.9339953882],"iteration":452,"passed_time":25.34192627,"remaining_time":30.60051583},
{"learn":[0.9318082172],"iteration":453,"passed_time":25.39443538,"remaining_time":30.54044431},
{"learn":[0.9291584404],"iteration":454,"passed_time":25.45047775,"remaining_time":30.48463819},
{"learn":[0.9271081338],"iteration":455,"passed_time":25.50350915,"remaining_time":30.42523898},
{"learn":[0.9258608882],"iteration":456,"passed_time":25.55228454,"remaining_time":30.36081073},
{"learn":[0.9237101853],"iteration":457,"passed_time":25.60811427,"remaining_time":30.30479899},
{"learn":[0.9214748194],"iteration":458,"passed_time":25.66226261,"remaining_time":30.24680626},
{"learn":[0.9187648775],"iteration":459,"passed_time":25.71871963,"remaining_time":30.19154044},
{"learn":[0.9164759451],"iteration":460,"passed_time":25.77156193,"remaining_time":30.13204313},
{"learn":[0.9142856569],"iteration":461,"passed_time":25.82588544,"remaining_time":30.07429949},
{"learn":[0.9130965382],"iteration":462,"passed_time":25.88179191,"remaining_time":30.0184066},
{"learn":[0.9107808133],"iteration":463,"passed_time":25.93405415,"remaining_time":29.95830393},
{"learn":[0.9092629422],"iteration":464,"passed_time":25.98543001,"remaining_time":29.89721518},
{"learn":[0.9068967666],"iteration":465,"passed_time":26.04176463,"remaining_time":29.84185046},
{"learn":[0.9055606875],"iteration":466,"passed_time":26.09439356,"remaining_time":29.78225218},
{"learn":[0.9039244363],"iteration":467,"passed_time":26.15053738,"remaining_time":29.72667924},
{"learn":[0.9018050247],"iteration":468,"passed_time":26.20708495,"remaining_time":29.671561},
{"learn":[0.9001726065],"iteration":469,"passed_time":26.25730329,"remaining_time":29.60929946},
{"learn":[0.8981125363],"iteration":470,"passed_time":26.31191229,"remaining_time":29.55202039},
{"learn":[0.8963347882],"iteration":471,"passed_time":26.37888068,"remaining_time":29.50857839},
{"learn":[0.894217455],"iteration":472,"passed_time":26.44726089,"remaining_time":29.46660991},
{"learn":[0.8929358299],"iteration":473,"passed_time":26.51626346,"remaining_time":29.42522063},
{"learn":[0.8918188615],"iteration":474,"passed_time":26.57497025,"remaining_time":29.37233554},
{"learn":[0.8906123284],"iteration":475,"passed_time":26.6306464,"remaining_time":29.31608973},
{"learn":[0.888442446],"iteration":476,"passed_time":26.68330457,"remaining_time":29.2565373},
{"learn":[0.8861682982],"iteration":477,"passed_time":26.73568567,"remaining_time":29.19671113},
{"learn":[0.8839535086],"iteration":478,"passed_time":26.7916783,"remaining_time":29.14084425},
{"learn":[0.8825049532],"iteration":479,"passed_time":26.84612419,"remaining_time":29.08330121},
{"learn":[0.8809118741],"iteration":480,"passed_time":26.89759678,"remaining_time":29.02256285},
{"learn":[0.8794679693],"iteration":481,"passed_time":26.94747216,"remaining_time":28.96014643},
{"learn":[0.87763449],"iteration":482,"passed_time":27.00414371,"remaining_time":28.90505652},
{"learn":[0.8752185463],"iteration":483,"passed_time":27.05589844,"remaining_time":28.84471817},
{"learn":[0.8727008077],"iteration":484,"passed_time":27.1137291,"remaining_time":28.79086698},
{"learn":[0.8710308853],"iteration":485,"passed_time":27.16441102,"remaining_time":28.72943882},
{"learn":[0.869169807],"iteration":486,"passed_time":27.21828533,"remaining_time":28.6714176},
{"learn":[0.8675022404],"iteration":487,"passed_time":27.27286658,"remaining_time":28.6141551},
{"learn":[0.8662002968],"iteration":488,"passed_time":27.32564197,"remaining_time":28.55501646},
{"learn":[0.8644915744],"iteration":489,"passed_time":27.38006038,"remaining_time":28.49761386},
{"learn":[0.8624770499],"iteration":490,"passed_time":27.43213034,"remaining_time":28.43778889},
{"learn":[0.860589511],"iteration":491,"passed_time":27.48516191,"remaining_time":28.37898831},
{"learn":[0.8591150593],"iteration":492,"passed_time":27.53841153,"remaining_time":28.32043539},
{"learn":[0.8574960882],"iteration":493,"passed_time":27.59388884,"remaining_time":28.26418573},
{"learn":[0.8563145939],"iteration":494,"passed_time":27.64551367,"remaining_time":28.20400889},
{"learn":[0.854211336],"iteration":495,"passed_time":27.70202957,"remaining_time":28.1488365},
{"learn":[0.8522372638],"iteration":496,"passed_time":27.75671765,"remaining_time":28.09180881},
{"learn":[0.8509320218],"iteration":497,"passed_time":27.81371745,"remaining_time":28.03712081},
{"learn":[0.8495132451],"iteration":498,"passed_time":27.8658253,"remaining_time":27.97751197},
{"learn":[0.8468666519],"iteration":499,"passed_time":27.91984868,"remaining_time":27.91984868},
{"learn":[0.8451793403],"iteration":500,"passed_time":27.97487894,"remaining_time":27.86320277},
{"learn":[0.8437634247],"iteration":501,"passed_time":28.02668772,"remaining_time":27.8033675},
{"learn":[0.8420158862],"iteration":502,"passed_time":28.08070722,"remaining_time":27.74574848},
{"learn":[0.8411566506],"iteration":503,"passed_time":28.13088823,"remaining_time":27.6843662},
{"learn":[0.8409386309],"iteration":504,"passed_time":28.18080985,"remaining_time":27.62277401},
{"learn":[0.8388816243],"iteration":505,"passed_time":28.23511424,"remaining_time":27.56550679},
{"learn":[0.8380738476],"iteration":506,"passed_time":28.28638745,"remaining_time":27.50530377},
{"learn":[0.8360874819],"iteration":507,"passed_time":28.36086275,"remaining_time":27.46760723},
{"learn":[0.8340025562],"iteration":508,"passed_time":28.42576252,"remaining_time":27.42052927},
{"learn":[0.8325069533],"iteration":509,"passed_time":28.48961933,"remaining_time":27.37237935},
{"learn":[0.8302220096],"iteration":510,"passed_time":28.55444849,"remaining_time":27.32509846},
{"learn":[0.8289066242],"iteration":511,"passed_time":28.60938538,"remaining_time":27.26832044},
{"learn":[0.8278348193],"iteration":512,"passed_time":28.68140361,"remaining_time":27.22776522},
{"learn":[0.826404069],"iteration":513,"passed_time":28.74730547,"remaining_time":27.1813044},
{"learn":[0.8251104197],"iteration":514,"passed_time":28.80934963,"remaining_time":27.13113509},
{"learn":[0.8238418265],"iteration":515,"passed_time":28.86700907,"remaining_time":27.07680696},
{"learn":[0.8222303308],"iteration":516,"passed_time":28.92807927,"remaining_time":27.0256524},
{"learn":[0.8204565694],"iteration":517,"passed_time":28.98630364,"remaining_time":26.97181149},
{"learn":[0.8184331279],"iteration":518,"passed_time":29.046018,"remaining_time":26.9193346},
{"learn":[0.8172717966],"iteration":519,"passed_time":29.09843016,"remaining_time":26.86008938},
{"learn":[0.8158171319],"iteration":520,"passed_time":29.16090076,"remaining_time":26.81011797},
{"learn":[0.813911892],"iteration":521,"passed_time":29.2196312,"remaining_time":26.75667378},
{"learn":[0.8121469955],"iteration":522,"passed_time":29.27582088,"remaining_time":26.70089209},
{"learn":[0.8101578835],"iteration":523,"passed_time":29.33266468,"remaining_time":26.64570303},
{"learn":[0.8090040817],"iteration":524,"passed_time":29.38956133,"remaining_time":26.59055549},
{"learn":[0.807795888],"iteration":525,"passed_time":29.45134169,"remaining_time":26.53980221},
{"learn":[0.8060313572],"iteration":526,"passed_time":29.50926495,"remaining_time":26.4855452},
{"learn":[0.8039772866],"iteration":527,"passed_time":29.56890098,"remaining_time":26.43280542},
{"learn":[0.8027045593],"iteration":528,"passed_time":29.62476227,"remaining_time":26.37667869},
{"learn":[0.8012331216],"iteration":529,"passed_time":29.67771375,"remaining_time":26.31797257},
{"learn":[0.7995071386],"iteration":530,"passed_time":29.73591744,"remaining_time":26.26392708},
{"learn":[0.7977465429],"iteration":531,"passed_time":29.80114816,"remaining_time":26.21604763},
{"learn":[0.7957084962],"iteration":532,"passed_time":29.85645933,"remaining_time":26.15941183},
{"learn":[0.7941672951],"iteration":533,"passed_time":29.91379917,"remaining_time":26.10455134},
{"learn":[0.7932971409],"iteration":534,"passed_time":29.97245055,"remaining_time":26.0508215},
{"learn":[0.7917229041],"iteration":535,"passed_time":30.02965943,"remaining_time":25.99582458},
{"learn":[0.7903956882],"iteration":536,"passed_time":30.0869967,"remaining_time":25.94093011},
{"learn":[0.7887809196],"iteration":537,"passed_time":30.14372223,"remaining_time":25.88550124},
{"learn":[0.7873418198],"iteration":538,"passed_time":30.19857946,"remaining_time":25.82846963},
{"learn":[0.785854539],"iteration":539,"passed_time":30.25628584,"remaining_time":25.77387312},
{"learn":[0.7842684492],"iteration":540,"passed_time":30.3115589,"remaining_time":25.71720062},
{"learn":[0.7828159879],"iteration":541,"passed_time":30.37142163,"remaining_time":25.66441164},
{"learn":[0.781361478],"iteration":542,"passed_time":30.42658154,"remaining_time":25.60763861},
{"learn":[0.7797634467],"iteration":543,"passed_time":30.48294639,"remaining_time":25.55188153},
{"learn":[0.7785013557],"iteration":544,"passed_time":30.53942649,"remaining_time":25.49621844},
{"learn":[0.7768937551],"iteration":545,"passed_time":30.59617786,"remaining_time":25.44077792},
{"learn":[0.7759578936],"iteration":546,"passed_time":30.65266922,"remaining_time":25.38511729},
{"learn":[0.7747568106],"iteration":547,"passed_time":30.7069434,"remaining_time":25.32762485},
{"learn":[0.773224783],"iteration":548,"passed_time":30.76408499,"remaining_time":25.27249969},
{"learn":[0.7715360728],"iteration":549,"passed_time":30.83006154,"remaining_time":25.22459581},
{"learn":[0.7710170873],"iteration":550,"passed_time":30.88544974,"remaining_time":25.16799806},
{"learn":[0.7695770842],"iteration":551,"passed_time":30.94501793,"remaining_time":25.11479716},
{"learn":[0.7680538293],"iteration":552,"passed_time":30.99965869,"remaining_time":25.0575903},
{"learn":[0.7662304488],"iteration":553,"passed_time":31.06361215,"remaining_time":25.00788993},
{"learn":[0.764378055],"iteration":554,"passed_time":31.12188477,"remaining_time":24.95358329},
{"learn":[0.7625301673],"iteration":555,"passed_time":31.17913566,"remaining_time":24.89844646},
{"learn":[0.7610293949],"iteration":556,"passed_time":31.23660366,"remaining_time":24.84347473},
{"learn":[0.7597322434],"iteration":557,"passed_time":31.30151354,"remaining_time":24.79438886},
{"learn":[0.7578898392],"iteration":558,"passed_time":31.36227003,"remaining_time":24.74196974},
{"learn":[0.7562781448],"iteration":559,"passed_time":31.42087216,"remaining_time":24.68782812},
{"learn":[0.7544917003],"iteration":560,"passed_time":31.47718137,"remaining_time":24.63187633},
{"learn":[0.7529257136],"iteration":561,"passed_time":31.52976078,"remaining_time":24.57301641},
{"learn":[0.7517193511],"iteration":562,"passed_time":31.58501028,"remaining_time":24.51625132},
{"learn":[0.749963156],"iteration":563,"passed_time":31.63839131,"remaining_time":24.45804719},
{"learn":[0.7490170696],"iteration":564,"passed_time":31.6970731,"remaining_time":24.40394123},
{"learn":[0.7480222941],"iteration":565,"passed_time":31.75116779,"remaining_time":24.3463018},
{"learn":[0.7469634183],"iteration":566,"passed_time":31.80676423,"remaining_time":24.28982172},
{"learn":[0.7458268014],"iteration":567,"passed_time":31.86281719,"remaining_time":24.23369195},
{"learn":[0.7442119488],"iteration":568,"passed_time":31.91716896,"remaining_time":24.17627385},
{"learn":[0.7433329031],"iteration":569,"passed_time":31.97271807,"remaining_time":24.11976977},
{"learn":[0.7417941833],"iteration":570,"passed_time":32.03341209,"remaining_time":24.06713447},
{"learn":[0.7405977953],"iteration":571,"passed_time":32.08974336,"remaining_time":24.01120657},
{"learn":[0.7390331623],"iteration":572,"passed_time":32.1433381,"remaining_time":23.95323799},
{"learn":[0.7374268142],"iteration":573,"passed_time":32.23902376,"remaining_time":23.92652286},
{"learn":[0.7365540083],"iteration":574,"passed_time":32.37109543,"remaining_time":23.92646184},
{"learn":[0.7353332093],"iteration":575,"passed_time":32.43050699,"remaining_time":23.87245654},
{"learn":[0.7343609637],"iteration":576,"passed_time":32.48503196,"remaining_time":23.81485012},
{"learn":[0.7332082789],"iteration":577,"passed_time":32.53744153,"remaining_time":23.7557099},
{"learn":[0.7327643252],"iteration":578,"passed_time":32.58891908,"remaining_time":23.69591525},
{"learn":[0.7308030418],"iteration":579,"passed_time":32.65160336,"remaining_time":23.6442645},
{"learn":[0.7290835377],"iteration":580,"passed_time":32.7092335,"remaining_time":23.58893087},
{"learn":[0.7281295033],"iteration":581,"passed_time":32.76579155,"remaining_time":23.53281936},
{"learn":[0.7273018089],"iteration":582,"passed_time":32.82126144,"remaining_time":23.475928},
{"learn":[0.7258129158],"iteration":583,"passed_time":32.87687866,"remaining_time":23.41914644},
{"learn":[0.7249581013],"iteration":584,"passed_time":32.93503021,"remaining_time":23.36416673},
{"learn":[0.7236901385],"iteration":585,"passed_time":32.98941702,"remaining_time":23.30651646},
{"learn":[0.7227876945],"iteration":586,"passed_time":33.0435728,"remaining_time":23.24871476},
{"learn":[0.7217302684],"iteration":587,"passed_time":33.09863788,"remaining_time":23.19156259},
{"learn":[0.7210289992],"iteration":588,"passed_time":33.1528699,"remaining_time":23.13383622},
{"learn":[0.7195864691],"iteration":589,"passed_time":33.2107651,"remaining_time":23.07866727},
{"learn":[0.7183904913],"iteration":590,"passed_time":33.26990155,"remaining_time":23.02434811},
{"learn":[0.716794254],"iteration":591,"passed_time":33.32939442,"remaining_time":22.97025832},
{"learn":[0.715849163],"iteration":592,"passed_time":33.3864785,"remaining_time":22.91449705},
{"learn":[0.7145014466],"iteration":593,"passed_time":33.4433332,"remaining_time":22.85857455},
{"learn":[0.7130790162],"iteration":594,"passed_time":33.5005326,"remaining_time":22.80288354},
{"learn":[0.7117728858],"iteration":595,"passed_time":33.55476745,"remaining_time":22.74517794},
{"learn":[0.7102162388],"iteration":596,"passed_time":33.61331319,"remaining_time":22.690394},
{"learn":[0.7091651041],"iteration":597,"passed_time":33.66700155,"remaining_time":22.63233214},
{"learn":[0.7078584377],"iteration":598,"passed_time":33.72518744,"remaining_time":22.57729577},
{"learn":[0.7065290487],"iteration":599,"passed_time":33.780875,"remaining_time":22.52058333},
{"learn":[0.7058723916],"iteration":600,"passed_time":33.8360934,"remaining_time":22.46356284},
{"learn":[0.704848854],"iteration":601,"passed_time":33.89573603,"remaining_time":22.40947332},
{"learn":[0.703083049],"iteration":602,"passed_time":33.95218382,"remaining_time":22.35326199},
{"learn":[0.7022353763],"iteration":603,"passed_time":34.01019449,"remaining_time":22.29807453},
{"learn":[0.7014590013],"iteration":604,"passed_time":34.06582845,"remaining_time":22.24132601},
{"learn":[0.6997508521],"iteration":605,"passed_time":34.12271038,"remaining_time":22.18539256},
{"learn":[0.6984510888],"iteration":606,"passed_time":34.18680685,"remaining_time":22.134127},
{"learn":[0.6972147792],"iteration":607,"passed_time":34.24099997,"remaining_time":22.07643419},
{"learn":[0.6959694107],"iteration":608,"passed_time":34.29917706,"remaining_time":22.02131072},
{"learn":[0.6950617997],"iteration":609,"passed_time":34.35291174,"remaining_time":21.96333701},
{"learn":[0.6936359275],"iteration":610,"passed_time":34.41092578,"remaining_time":21.90810168},
{"learn":[0.6924729548],"iteration":611,"passed_time":34.46526108,"remaining_time":21.850525},
{"learn":[0.6909806418],"iteration":612,"passed_time":34.52109513,"remaining_time":21.79390509},
{"learn":[0.69011668],"iteration":613,"passed_time":34.57723798,"remaining_time":21.73748186},
{"learn":[0.6892191063],"iteration":614,"passed_time":34.63258586,"remaining_time":21.68056188},
{"learn":[0.6877183361],"iteration":615,"passed_time":34.69159034,"remaining_time":21.62592644},
{"learn":[0.6865847332],"iteration":616,"passed_time":34.74766885,"remaining_time":21.56946057},
{"learn":[0.6853347758],"iteration":617,"passed_time":34.80348606,"remaining_time":21.51283442},
{"learn":[0.6838940769],"iteration":618,"passed_time":34.86514522,"remaining_time":21.45980667},
{"learn":[0.6827800447],"iteration":619,"passed_time":34.92003824,"remaining_time":21.40260408},
{"learn":[0.6817194993],"iteration":620,"passed_time":34.97746177,"remaining_time":21.34695332},
{"learn":[0.6812277951],"iteration":621,"passed_time":35.03081971,"remaining_time":21.28882613},
{"learn":[0.6796490141],"iteration":622,"passed_time":35.08800716,"remaining_time":21.23303162},
{"learn":[0.6786570407],"iteration":623,"passed_time":35.14181566,"remaining_time":21.17519661},
{"learn":[0.6771282778],"iteration":624,"passed_time":35.20161807,"remaining_time":21.12097084},
{"learn":[0.6758553679],"iteration":625,"passed_time":35.26165256,"remaining_time":21.0668659},
{"learn":[0.6754063287],"iteration":626,"passed_time":35.31646733,"remaining_time":21.00963687},
{"learn":[0.6746593449],"iteration":627,"passed_time":35.37146538,"remaining_time":20.95252408},
{"learn":[0.6733348711],"iteration":628,"passed_time":35.4350472,"remaining_time":20.90048094},
{"learn":[0.6724304577],"iteration":629,"passed_time":35.49126381,"remaining_time":20.84407557},
{"learn":[0.6709344025],"iteration":630,"passed_time":35.55156517,"remaining_time":20.79005951},
{"learn":[0.6704534382],"iteration":631,"passed_time":35.60242393,"remaining_time":20.73052533},
{"learn":[0.6692943928],"iteration":632,"passed_time":35.65691446,"remaining_time":20.67312418},
{"learn":[0.6679916219],"iteration":633,"passed_time":35.70698455,"remaining_time":20.61318036},
{"learn":[0.6667507009],"iteration":634,"passed_time":35.76247213,"remaining_time":20.55638162},
{"learn":[0.6658730307],"iteration":635,"passed_time":35.81384998,"remaining_time":20.49723489},
{"learn":[0.6645003429],"iteration":636,"passed_time":35.8685746,"remaining_time":20.44001975},
{"learn":[0.6630734452],"iteration":637,"passed_time":35.92614619,"remaining_time":20.38442778},
{"learn":[0.6616488314],"iteration":638,"passed_time":35.97957254,"remaining_time":20.32648777},
{"learn":[0.6604006794],"iteration":639,"passed_time":36.03322077,"remaining_time":20.26868668},
{"learn":[0.6587478785],"iteration":640,"passed_time":36.08572943,"remaining_time":20.21026032},
{"learn":[0.6574023578],"iteration":641,"passed_time":36.13763754,"remaining_time":20.15151751},
{"learn":[0.6565771364],"iteration":642,"passed_time":36.19333191,"remaining_time":20.09489812},
{"learn":[0.6553703762],"iteration":643,"passed_time":36.24397451,"remaining_time":20.03548901},
{"learn":[0.6542542957],"iteration":644,"passed_time":36.29625662,"remaining_time":19.97700946},
{"learn":[0.6529390847],"iteration":645,"passed_time":36.35281175,"remaining_time":19.92089065},
{"learn":[0.6515874686],"iteration":646,"passed_time":36.40602063,"remaining_time":19.86294479},
{"learn":[0.650754698],"iteration":647,"passed_time":36.46274487,"remaining_time":19.80692314},
{"learn":[0.6493633461],"iteration":648,"passed_time":36.52243754,"remaining_time":19.75250474},
{"learn":[0.6487167081],"iteration":649,"passed_time":36.57717366,"remaining_time":19.6954012},
{"learn":[0.6479305343],"iteration":650,"passed_time":36.63112562,"remaining_time":19.63788455},
{"learn":[0.6465180713],"iteration":651,"passed_time":36.68613368,"remaining_time":19.58094252},
{"learn":[0.645266149],"iteration":652,"passed_time":36.74271535,"remaining_time":19.52484262},
{"learn":[0.6441856081],"iteration":653,"passed_time":36.79586373,"remaining_time":19.46692485},
{"learn":[0.6431832528],"iteration":654,"passed_time":36.84703744,"remaining_time":19.40798155},
{"learn":[0.641787049],"iteration":655,"passed_time":36.90865013,"remaining_time":19.35453605},
{"learn":[0.6409028606],"iteration":656,"passed_time":36.95860981,"remaining_time":19.29498199},
{"learn":[0.6396345283],"iteration":657,"passed_time":37.02016085,"remaining_time":19.24148178},
{"learn":[0.6386857765],"iteration":658,"passed_time":37.07306586,"remaining_time":19.18348324},
{"learn":[0.6381112508],"iteration":659,"passed_time":37.12650019,"remaining_time":19.12577283},
{"learn":[0.6366719325],"iteration":660,"passed_time":37.18430531,"remaining_time":19.07031694},
{"learn":[0.6359994673],"iteration":661,"passed_time":37.23632318,"remaining_time":19.01189915},
{"learn":[0.6348846842],"iteration":662,"passed_time":37.29090941,"remaining_time":18.95480614},
{"learn":[0.6339563041],"iteration":663,"passed_time":37.34143477,"remaining_time":18.89566579},
{"learn":[0.6328130419],"iteration":664,"passed_time":37.39303578,"remaining_time":18.83709321},
{"learn":[0.6317813595],"iteration":665,"passed_time":37.44842378,"remaining_time":18.78044075},
{"learn":[0.6305929229],"iteration":666,"passed_time":37.5040276,"remaining_time":18.72389984},
{"learn":[0.6297590361],"iteration":667,"passed_time":37.55486378,"remaining_time":18.66499218},
{"learn":[0.6290107401],"iteration":668,"passed_time":37.61172563,"remaining_time":18.60908996},
{"learn":[0.6279030914],"iteration":669,"passed_time":37.66518788,"remaining_time":18.55151045},
{"learn":[0.6269557298],"iteration":670,"passed_time":37.72202122,"remaining_time":18.4955961},
{"learn":[0.6260457634],"iteration":671,"passed_time":37.77247164,"remaining_time":18.43656354},
{"learn":[0.6252162978],"iteration":672,"passed_time":37.82544253,"remaining_time":18.37878114},
{"learn":[0.6241214526],"iteration":673,"passed_time":37.88575916,"remaining_time":18.324566},
{"learn":[0.6229087134],"iteration":674,"passed_time":37.94393227,"remaining_time":18.26930072},
{"learn":[0.6223166325],"iteration":675,"passed_time":38.00223912,"remaining_time":18.21409094},
{"learn":[0.6209541381],"iteration":676,"passed_time":38.05686949,"remaining_time":18.15711794},
{"learn":[0.6200849955],"iteration":677,"passed_time":38.11343485,"remaining_time":18.10107083},
{"learn":[0.6191803022],"iteration":678,"passed_time":38.17195247,"remaining_time":18.04594513},
{"learn":[0.6178487952],"iteration":679,"passed_time":38.22721104,"remaining_time":17.98927578},
{"learn":[0.6170781607],"iteration":680,"passed_time":38.28787389,"remaining_time":17.9351421},
{"learn":[0.6159937229],"iteration":681,"passed_time":38.3381819,"remaining_time":17.87616106},
{"learn":[0.614508546],"iteration":682,"passed_time":38.39455373,"remaining_time":17.82001981},
{"learn":[0.6131251307],"iteration":683,"passed_time":38.45238783,"remaining_time":17.76455344},
{"learn":[0.611898564],"iteration":684,"passed_time":38.50704959,"remaining_time":17.70762135},
{"learn":[0.6110639671],"iteration":685,"passed_time":38.56476359,"remaining_time":17.65209295},
{"learn":[0.6098640884],"iteration":686,"passed_time":38.61901179,"remaining_time":17.59497917},
{"learn":[0.6089853689],"iteration":687,"passed_time":38.67229678,"remaining_time":17.53743691},
{"learn":[0.6080162499],"iteration":688,"passed_time":38.72696969,"remaining_time":17.48053349},
{"learn":[0.606789931],"iteration":689,"passed_time":38.78835557,"remaining_time":17.4266525},
{"learn":[0.6059957603],"iteration":690,"passed_time":38.84447762,"remaining_time":17.37039592},
{"learn":[0.6045860343],"iteration":691,"passed_time":38.89512033,"remaining_time":17.31170096},
{"learn":[0.6038683774],"iteration":692,"passed_time":38.94677515,"remaining_time":17.25347759},
{"learn":[0.602714559],"iteration":693,"passed_time":38.9996677,"remaining_time":17.1958189},
{"learn":[0.6022282786],"iteration":694,"passed_time":39.04994071,"remaining_time":17.13702434},
{"learn":[0.601606312],"iteration":695,"passed_time":39.10040052,"remaining_time":17.07833586},
{"learn":[0.6005620881],"iteration":696,"passed_time":39.15844131,"remaining_time":17.02296659},
{"learn":[0.5993485994],"iteration":697,"passed_time":39.21277762,"remaining_time":16.96598688},
{"learn":[0.5982714865],"iteration":698,"passed_time":39.26927326,"remaining_time":16.90994456},
{"learn":[0.597023376],"iteration":699,"passed_time":39.3235479,"remaining_time":16.8529491},
{"learn":[0.5963270045],"iteration":700,"passed_time":39.37693298,"remaining_time":16.79558197},
{"learn":[0.5952461813],"iteration":701,"passed_time":39.43459645,"remaining_time":16.74004237},
{"learn":[0.5943565273],"iteration":702,"passed_time":39.48448727,"remaining_time":16.68121297},
{"learn":[0.593440403],"iteration":703,"passed_time":39.53759266,"remaining_time":16.62376055},
{"learn":[0.5928786522],"iteration":704,"passed_time":39.59283927,"remaining_time":16.56721643},
{"learn":[0.5924423972],"iteration":705,"passed_time":39.64567774,"remaining_time":16.50967317},
{"learn":[0.591517088],"iteration":706,"passed_time":39.69949731,"remaining_time":16.4525498},
{"learn":[0.5909791674],"iteration":707,"passed_time":39.74959689,"remaining_time":16.39390154},
{"learn":[0.5902926809],"iteration":708,"passed_time":39.80166065,"remaining_time":16.33608357},
{"learn":[0.589850465],"iteration":709,"passed_time":39.85582045,"remaining_time":16.27913793},
{"learn":[0.5889702349],"iteration":710,"passed_time":39.90989934,"remaining_time":16.22216724},
{"learn":[0.5879547354],"iteration":711,"passed_time":39.96451901,"remaining_time":16.16542342},
{"learn":[0.5869036929],"iteration":712,"passed_time":40.01765655,"remaining_time":16.10808896},
{"learn":[0.5855935325],"iteration":713,"passed_time":40.08151448,"remaining_time":16.05506042},
{"learn":[0.5850299725],"iteration":714,"passed_time":40.13317754,"remaining_time":15.9971407},
{"learn":[0.5841974046],"iteration":715,"passed_time":40.18690507,"remaining_time":15.94005732},
{"learn":[0.5836612502],"iteration":716,"passed_time":40.23623186,"remaining_time":15.88124633},
{"learn":[0.582585711],"iteration":717,"passed_time":40.28992551,"remaining_time":15.82417687},
{"learn":[0.581934078],"iteration":718,"passed_time":40.34323023,"remaining_time":15.76696481},
{"learn":[0.5813163257],"iteration":719,"passed_time":40.3949855,"remaining_time":15.70916103},
{"learn":[0.5801371096],"iteration":720,"passed_time":40.44950358,"remaining_time":15.65244313},
{"learn":[0.5793745138],"iteration":721,"passed_time":40.50569864,"remaining_time":15.59637704},
{"learn":[0.5783355766],"iteration":722,"passed_time":40.55906967,"remaining_time":15.53922863},
{"learn":[0.5774782014],"iteration":723,"passed_time":40.6132578,"remaining_time":15.48240214},
{"learn":[0.5766942768],"iteration":724,"passed_time":40.66807632,"remaining_time":15.42582205},
{"learn":[0.575451866],"iteration":725,"passed_time":40.72259164,"remaining_time":15.36913238},
{"learn":[0.5747353863],"iteration":726,"passed_time":40.77810055,"remaining_time":15.3128218},
{"learn":[0.5740070667],"iteration":727,"passed_time":40.82782932,"remaining_time":15.25435381},
{"learn":[0.5732849157],"iteration":728,"passed_time":40.88306605,"remaining_time":15.19795734},
{"learn":[0.5722486003],"iteration":729,"passed_time":40.93720777,"remaining_time":15.14115904},
{"learn":[0.571143403],"iteration":730,"passed_time":40.99094041,"remaining_time":15.08421747},
{"learn":[0.5703770138],"iteration":731,"passed_time":41.04821625,"remaining_time":15.0285819},
{"learn":[0.5693427257],"iteration":732,"passed_time":41.10643867,"remaining_time":14.97328666},
{"learn":[0.5683760114],"iteration":733,"passed_time":41.16631531,"remaining_time":14.91858293},
{"learn":[0.5675141812],"iteration":734,"passed_time":41.2211138,"remaining_time":14.86203423},
{"learn":[0.5665507236],"iteration":735,"passed_time":41.27488342,"remaining_time":14.80512123},
{"learn":[0.5657808678],"iteration":736,"passed_time":41.32994406,"remaining_time":14.74867746},
{"learn":[0.5650737045],"iteration":737,"passed_time":41.38242437,"remaining_time":14.69132139},
{"learn":[0.5642489626],"iteration":738,"passed_time":41.44051792,"remaining_time":14.635961},
{"learn":[0.5633952922],"iteration":739,"passed_time":41.49741664,"remaining_time":14.58017341},
{"learn":[0.5628666842],"iteration":740,"passed_time":41.54885997,"remaining_time":14.52247602},
{"learn":[0.5623169424],"iteration":741,"passed_time":41.60693907,"remaining_time":14.4671028},
{"learn":[0.5612787331],"iteration":742,"passed_time":41.65973317,"remaining_time":14.40989425},
{"learn":[0.5606019356],"iteration":743,"passed_time":41.71398084,"remaining_time":14.35319771},
{"learn":[0.5600090043],"iteration":744,"passed_time":41.7661782,"remaining_time":14.29580596},
{"learn":[0.5591161408],"iteration":745,"passed_time":41.81591097,"remaining_time":14.23758899},
{"learn":[0.5582885999],"iteration":746,"passed_time":41.87443692,"remaining_time":14.18237288},
{"learn":[0.5573433631],"iteration":747,"passed_time":41.92816111,"remaining_time":14.12553021},
{"learn":[0.5567162105],"iteration":748,"passed_time":41.98128871,"remaining_time":14.06849595},
{"learn":[0.5560970169],"iteration":749,"passed_time":42.03948536,"remaining_time":14.01316179},
{"learn":[0.5553184184],"iteration":750,"passed_time":42.09572947,"remaining_time":13.95717262},
{"learn":[0.5546253623],"iteration":751,"passed_time":42.15112962,"remaining_time":13.90090445},
{"learn":[0.554172777],"iteration":752,"passed_time":42.20441259,"remaining_time":13.8439441},
{"learn":[0.553547031],"iteration":753,"passed_time":42.25635503,"remaining_time":13.78655615},
{"learn":[0.5526373997],"iteration":754,"passed_time":42.31328335,"remaining_time":13.73080056},
{"learn":[0.5518255295],"iteration":755,"passed_time":42.36740879,"remaining_time":13.67413723},
{"learn":[0.5508026141],"iteration":756,"passed_time":42.42857758,"remaining_time":13.61974155},
{"learn":[0.5495279027],"iteration":757,"passed_time":42.48645315,"remaining_time":13.5642766},
{"learn":[0.5487572855],"iteration":758,"passed_time":42.54461793,"remaining_time":13.50889713},
{"learn":[0.5477333398],"iteration":759,"passed_time":42.60135928,"remaining_time":13.45306082},
{"learn":[0.5469957221],"iteration":760,"passed_time":42.65247129,"remaining_time":13.39545419},
{"learn":[0.5460398358],"iteration":761,"passed_time":42.70778611,"remaining_time":13.33917729},
{"learn":[0.5449711267],"iteration":762,"passed_time":42.76240214,"remaining_time":13.28268585},
{"learn":[0.5440313915],"iteration":763,"passed_time":42.81798438,"remaining_time":13.22649779},
{"learn":[0.5433217769],"iteration":764,"passed_time":42.87732899,"remaining_time":13.17146708},
{"learn":[0.543069045],"iteration":765,"passed_time":42.93166704,"remaining_time":13.11489567},
{"learn":[0.5421902459],"iteration":766,"passed_time":42.98572371,"remaining_time":13.05824462},
{"learn":[0.5418575932],"iteration":767,"passed_time":43.03651181,"remaining_time":13.00061294},
{"learn":[0.5409932328],"iteration":768,"passed_time":43.09057197,"remaining_time":12.94398196},
{"learn":[0.5401069093],"iteration":769,"passed_time":43.1416753,"remaining_time":12.88647444},
{"learn":[0.5394835469],"iteration":770,"passed_time":43.19867301,"remaining_time":12.83073427},
{"learn":[0.5385837003],"iteration":771,"passed_time":43.25127811,"remaining_time":12.77369354},
{"learn":[0.538237667],"iteration":772,"passed_time":43.30168008,"remaining_time":12.71601731},
{"learn":[0.5372615369],"iteration":773,"passed_time":43.35552989,"remaining_time":12.65936661},
{"learn":[0.5363012407],"iteration":774,"passed_time":43.40641176,"remaining_time":12.60186148},
{"learn":[0.5358641166],"iteration":775,"passed_time":43.46261381,"remaining_time":12.54590914},
{"learn":[0.5347732232],"iteration":776,"passed_time":43.51483454,"remaining_time":12.48881352},
{"learn":[0.534296317],"iteration":777,"passed_time":43.56559994,"remaining_time":12.43131515},
{"learn":[0.533507991],"iteration":778,"passed_time":43.62102511,"remaining_time":12.37515603},
{"learn":[0.532519713],"iteration":779,"passed_time":43.67156665,"remaining_time":12.31762136},
{"learn":[0.5317725514],"iteration":780,"passed_time":43.72825685,"remaining_time":12.26182875},
{"learn":[0.530774686],"iteration":781,"passed_time":43.78298143,"remaining_time":12.20548587},
{"learn":[0.5300222115],"iteration":782,"passed_time":43.83441849,"remaining_time":12.14823603},
{"learn":[0.5297201389],"iteration":783,"passed_time":43.887742,"remaining_time":12.09152076},
{"learn":[0.5291059097],"iteration":784,"passed_time":43.9372206,"remaining_time":12.03376106},
{"learn":[0.5289994441],"iteration":785,"passed_time":43.98587061,"remaining_time":11.97579683},
{"learn":[0.5282436858],"iteration":786,"passed_time":44.04230465,"remaining_time":11.91996301},
{"learn":[0.5275237441],"iteration":787,"passed_time":44.09572215,"remaining_time":11.86331611},
{"learn":[0.526775483],"iteration":788,"passed_time":44.15360479,"remaining_time":11.8078715},
{"learn":[0.5260636793],"iteration":789,"passed_time":44.20534033,"remaining_time":11.75078667},
{"learn":[0.525246422],"iteration":790,"passed_time":44.25924889,"remaining_time":11.69428953},
{"learn":[0.5245934819],"iteration":791,"passed_time":44.31545429,"remaining_time":11.63840214},
{"learn":[0.5242628074],"iteration":792,"passed_time":44.36631431,"remaining_time":11.58111862},
{"learn":[0.5234657829],"iteration":793,"passed_time":44.41866692,"remaining_time":11.52423852},
{"learn":[0.5226749771],"iteration":794,"passed_time":44.47429517,"remaining_time":11.46821448},
{"learn":[0.5217901209],"iteration":795,"passed_time":44.52873323,"remaining_time":11.4118864},
{"learn":[0.5208303931],"iteration":796,"passed_time":44.58482336,"remaining_time":11.35598387},
{"learn":[0.5200264774],"iteration":797,"passed_time":44.63651157,"remaining_time":11.29896659},
{"learn":[0.5194402838],"iteration":798,"passed_time":44.69214054,"remaining_time":11.242954},
{"learn":[0.5184802671],"iteration":799,"passed_time":44.74593897,"remaining_time":11.18648474},
{"learn":[0.5179683825],"iteration":800,"passed_time":44.79468279,"remaining_time":11.12876639},
{"learn":[0.5170925643],"iteration":801,"passed_time":44.84898425,"remaining_time":11.0724425},
{"learn":[0.5163317664],"iteration":802,"passed_time":44.90253001,"remaining_time":11.01593825},
{"learn":[0.5154272573],"iteration":803,"passed_time":44.95914157,"remaining_time":10.96018874},
{"learn":[0.515010693],"iteration":804,"passed_time":45.01043068,"remaining_time":10.9031478},
{"learn":[0.5142406586],"iteration":805,"passed_time":45.06535054,"remaining_time":10.84699504},
{"learn":[0.5133812069],"iteration":806,"passed_time":45.1153815,"remaining_time":10.78967612},
{"learn":[0.5126354764],"iteration":807,"passed_time":45.16936077,"remaining_time":10.73331345},
{"learn":[0.5122621423],"iteration":808,"passed_time":45.22055963,"remaining_time":10.67630023},
{"learn":[0.5117997294],"iteration":809,"passed_time":45.27213889,"remaining_time":10.6193906},
{"learn":[0.5113066338],"iteration":810,"passed_time":45.3263114,"remaining_time":10.56309846},
{"learn":[0.510358043],"iteration":811,"passed_time":45.38066733,"remaining_time":10.50685401},
{"learn":[0.5094432562],"iteration":812,"passed_time":45.43529998,"remaining_time":10.45067785},
{"learn":[0.5086891022],"iteration":813,"passed_time":45.48925162,"remaining_time":10.39434988},
{"learn":[0.5081289775],"iteration":814,"passed_time":45.54062807,"remaining_time":10.33744318},
{"learn":[0.507222405],"iteration":815,"passed_time":45.60015099,"remaining_time":10.28238699},
{"learn":[0.5065302378],"iteration":816,"passed_time":45.65226733,"remaining_time":10.22566086},
{"learn":[0.506401872],"iteration":817,"passed_time":45.70587658,"remaining_time":10.16927816},
{"learn":[0.5054937485],"iteration":818,"passed_time":45.75500916,"remaining_time":10.11191289},
{"learn":[0.504662024],"iteration":819,"passed_time":45.80893895,"remaining_time":10.05562074},
{"learn":[0.5040157308],"iteration":820,"passed_time":45.86374886,"remaining_time":9.999526244},
{"learn":[0.5032670499],"iteration":821,"passed_time":45.91663119,"remaining_time":9.943017461},
{"learn":[0.5026499009],"iteration":822,"passed_time":45.97019085,"remaining_time":9.88666316},
{"learn":[0.502159445],"iteration":823,"passed_time":46.02599022,"remaining_time":9.830794027},
{"learn":[0.5013765669],"iteration":824,"passed_time":46.08078109,"remaining_time":9.774711141},
{"learn":[0.5004336158],"iteration":825,"passed_time":46.13574116,"remaining_time":9.718667024},
{"learn":[0.4997033531],"iteration":826,"passed_time":46.18853678,"remaining_time":9.662172748},
{"learn":[0.4989969406],"iteration":827,"passed_time":46.2417745,"remaining_time":9.605779244},
{"learn":[0.498507531],"iteration":828,"passed_time":46.29734024,"remaining_time":9.54987356},
{"learn":[0.497675603],"iteration":829,"passed_time":46.35124912,"remaining_time":9.493629338},
{"learn":[0.4969666502],"iteration":830,"passed_time":46.40698372,"remaining_time":9.437762031},
{"learn":[0.4964005604],"iteration":831,"passed_time":46.45587974,"remaining_time":9.380514179},
{"learn":[0.4958773888],"iteration":832,"passed_time":46.51510938,"remaining_time":9.325358062},
{"learn":[0.4949597112],"iteration":833,"passed_time":46.67530193,"remaining_time":9.290287914},
{"learn":[0.4944158898],"iteration":834,"passed_time":46.72991175,"remaining_time":9.234054417},
{"learn":[0.4939651184],"iteration":835,"passed_time":46.78144144,"remaining_time":9.17722057},
{"learn":[0.4931322577],"iteration":836,"passed_time":46.83582476,"remaining_time":9.12095512},
{"learn":[0.4927871594],"iteration":837,"passed_time":46.89206605,"remaining_time":9.06505334},
{"learn":[0.4925715889],"iteration":838,"passed_time":46.9400914,"remaining_time":9.007574154},
{"learn":[0.4918717042],"iteration":839,"passed_time":46.99170891,"remaining_time":8.950801696},
{"learn":[0.4913973583],"iteration":840,"passed_time":47.04719973,"remaining_time":8.89477379},
{"learn":[0.4907428172],"iteration":841,"passed_time":47.10569934,"remaining_time":8.839311752},
{"learn":[0.4905598872],"iteration":842,"passed_time":47.15728719,"remaining_time":8.782555266},
{"learn":[0.490027849],"iteration":843,"passed_time":47.20719394,"remaining_time":8.725500302},
{"learn":[0.4892642638],"iteration":844,"passed_time":47.26031883,"remaining_time":8.669052566},
{"learn":[0.4883680262],"iteration":845,"passed_time":47.31667504,"remaining_time":8.613200895},
{"learn":[0.4877127894],"iteration":846,"passed_time":47.36761039,"remaining_time":8.556368819},
{"learn":[0.4869712654],"iteration":847,"passed_time":47.41868115,"remaining_time":8.499574923},
{"learn":[0.4862859561],"iteration":848,"passed_time":47.47279437,"remaining_time":8.44333563},
{"learn":[0.4855918976],"iteration":849,"passed_time":47.52381275,"remaining_time":8.386555191},
{"learn":[0.4847530932],"iteration":850,"passed_time":47.57907128,"remaining_time":8.330530694},
{"learn":[0.4841435673],"iteration":851,"passed_time":47.62957582,"remaining_time":8.273682184},
{"learn":[0.4833536157],"iteration":852,"passed_time":47.68419633,"remaining_time":8.217557867},
{"learn":[0.4826548474],"iteration":853,"passed_time":47.73950157,"remaining_time":8.161554133},
{"learn":[0.4817796159],"iteration":854,"passed_time":47.79160897,"remaining_time":8.105009708},
{"learn":[0.4808331924],"iteration":855,"passed_time":47.84556696,"remaining_time":8.048786965},
{"learn":[0.4800921823],"iteration":856,"passed_time":47.89719464,"remaining_time":7.99218067},
{"learn":[0.4791709356],"iteration":857,"passed_time":47.95148123,"remaining_time":7.936026031},
{"learn":[0.4788960615],"iteration":858,"passed_time":48.00230082,"remaining_time":7.879306654},
{"learn":[0.4783157642],"iteration":859,"passed_time":48.05286833,"remaining_time":7.822559961},
{"learn":[0.4778295249],"iteration":860,"passed_time":48.10393855,"remaining_time":7.765908778},
{"learn":[0.4777143556],"iteration":861,"passed_time":48.15532729,"remaining_time":7.709321538},
{"learn":[0.4771026604],"iteration":862,"passed_time":48.20666419,"remaining_time":7.652738115},
{"learn":[0.4763100495],"iteration":863,"passed_time":48.26331122,"remaining_time":7.597002692},
{"learn":[0.4753928583],"iteration":864,"passed_time":48.318088,"remaining_time":7.540973271},
{"learn":[0.4745038004],"iteration":865,"passed_time":48.37138915,"remaining_time":7.484718413},
{"learn":[0.4736733176],"iteration":866,"passed_time":48.42540152,"remaining_time":7.428579471},
{"learn":[0.4729592122],"iteration":867,"passed_time":48.47664404,"remaining_time":7.372024209},
{"learn":[0.4725767879],"iteration":868,"passed_time":48.53022821,"remaining_time":7.315834172},
{"learn":[0.4717045578],"iteration":869,"passed_time":48.58531054,"remaining_time":7.259873988},
{"learn":[0.4709964801],"iteration":870,"passed_time":48.63775464,"remaining_time":7.203525084},
{"learn":[0.4704953017],"iteration":871,"passed_time":48.69192809,"remaining_time":7.147438985},
{"learn":[0.4696868554],"iteration":872,"passed_time":48.74603807,"remaining_time":7.091348035},
{"learn":[0.4692358725],"iteration":873,"passed_time":48.79768244,"remaining_time":7.034906164},
{"learn":[0.4687747439],"iteration":874,"passed_time":48.85013521,"remaining_time":6.978590744},
{"learn":[0.4683246947],"iteration":875,"passed_time":48.90102071,"remaining_time":6.922062293},
{"learn":[0.4674801737],"iteration":876,"passed_time":48.95196747,"remaining_time":6.865555301},
{"learn":[0.4667921277],"iteration":877,"passed_time":49.00846853,"remaining_time":6.809832757},
{"learn":[0.4660267685],"iteration":878,"passed_time":49.0613691,"remaining_time":6.753612812},
{"learn":[0.4653161774],"iteration":879,"passed_time":49.11532762,"remaining_time":6.697544676},
{"learn":[0.4646904837],"iteration":880,"passed_time":49.16867793,"remaining_time":6.641399176},
{"learn":[0.4641631566],"iteration":881,"passed_time":49.22355707,"remaining_time":6.585464551},
{"learn":[0.4637526709],"iteration":882,"passed_time":49.27793252,"remaining_time":6.529465577},
{"learn":[0.4633254353],"iteration":883,"passed_time":49.33388756,"remaining_time":6.473677554},
{"learn":[0.4629610674],"iteration":884,"passed_time":49.38323587,"remaining_time":6.41703065},
{"learn":[0.4624757316],"iteration":885,"passed_time":49.43512904,"remaining_time":6.360727664},
{"learn":[0.4619166999],"iteration":886,"passed_time":49.48690991,"remaining_time":6.304420316},
{"learn":[0.4613373452],"iteration":887,"passed_time":49.54208136,"remaining_time":6.248550802},
{"learn":[0.4607897771],"iteration":888,"passed_time":49.59422333,"remaining_time":6.1923046},
{"learn":[0.4602331891],"iteration":889,"passed_time":49.64669835,"remaining_time":6.136108785},
{"learn":[0.4596590239],"iteration":890,"passed_time":49.70115385,"remaining_time":6.080163603},
{"learn":[0.4591435373],"iteration":891,"passed_time":49.75266616,"remaining_time":6.023865409},
{"learn":[0.4589361727],"iteration":892,"passed_time":49.80573711,"remaining_time":5.967764693},
{"learn":[0.45825653],"iteration":893,"passed_time":49.87014609,"remaining_time":5.913015084},
{"learn":[0.4580452096],"iteration":894,"passed_time":49.93489996,"remaining_time":5.858284352},
{"learn":[0.4577791452],"iteration":895,"passed_time":50.00174065,"remaining_time":5.803773468},
{"learn":[0.4571755092],"iteration":896,"passed_time":50.06662174,"remaining_time":5.749010077},
{"learn":[0.4564815212],"iteration":897,"passed_time":50.13253317,"remaining_time":5.694341185},
{"learn":[0.4562207018],"iteration":898,"passed_time":50.19200278,"remaining_time":5.638923561},
{"learn":[0.4561036584],"iteration":899,"passed_time":50.26064765,"remaining_time":5.584516405},
{"learn":[0.45532516],"iteration":900,"passed_time":50.32003792,"remaining_time":5.52906077},
{"learn":[0.4545799269],"iteration":901,"passed_time":50.37776203,"remaining_time":5.473415387},
{"learn":[0.4540513763],"iteration":902,"passed_time":50.43276157,"remaining_time":5.417472727},
{"learn":[0.453757351],"iteration":903,"passed_time":50.48697686,"remaining_time":5.36144887},
{"learn":[0.4532220769],"iteration":904,"passed_time":50.54275113,"remaining_time":5.305592661},
{"learn":[0.4525325997],"iteration":905,"passed_time":50.5953353,"remaining_time":5.249405649},
{"learn":[0.4522655363],"iteration":906,"passed_time":50.64632089,"remaining_time":5.193062671},
{"learn":[0.4514520781],"iteration":907,"passed_time":50.70681997,"remaining_time":5.137695415},
{"learn":[0.4508898524],"iteration":908,"passed_time":50.7595758,"remaining_time":5.081541692},
{"learn":[0.4505245217],"iteration":909,"passed_time":50.81167998,"remaining_time":5.025330987},
{"learn":[0.4498769249],"iteration":910,"passed_time":50.87543986,"remaining_time":4.970268},
{"learn":[0.4492619551],"iteration":911,"passed_time":50.9421602,"remaining_time":4.915471598},
{"learn":[0.4485894036],"iteration":912,"passed_time":51.01661652,"remaining_time":4.86138624},
{"learn":[0.447970252],"iteration":913,"passed_time":51.09173124,"remaining_time":4.807318257},
{"learn":[0.4476684216],"iteration":914,"passed_time":51.15386317,"remaining_time":4.751998218},
{"learn":[0.4469316399],"iteration":915,"passed_time":51.23610519,"remaining_time":4.698507463},
{"learn":[0.4463689979],"iteration":916,"passed_time":51.29249482,"remaining_time":4.642614035},
{"learn":[0.4459997915],"iteration":917,"passed_time":51.34635925,"remaining_time":4.586493964},
{"learn":[0.4453166141],"iteration":918,"passed_time":51.4094197,"remaining_time":4.531189331},
{"learn":[0.4447915667],"iteration":919,"passed_time":51.47173043,"remaining_time":4.475802646},
{"learn":[0.4440879749],"iteration":920,"passed_time":51.52669197,"remaining_time":4.419770538},
{"learn":[0.443596632],"iteration":921,"passed_time":51.58474991,"remaining_time":4.364002704},
{"learn":[0.4428823939],"iteration":922,"passed_time":51.64912467,"remaining_time":4.308756879},
{"learn":[0.4423047108],"iteration":923,"passed_time":51.71020315,"remaining_time":4.253220173},
{"learn":[0.4416432183],"iteration":924,"passed_time":51.77202259,"remaining_time":4.197731561},
{"learn":[0.4414731565],"iteration":925,"passed_time":51.82887313,"remaining_time":4.141832194},
{"learn":[0.4409425813],"iteration":926,"passed_time":51.89013928,"remaining_time":4.086278498},
{"learn":[0.4403844834],"iteration":927,"passed_time":51.94943772,"remaining_time":4.030559823},
{"learn":[0.4402601337],"iteration":928,"passed_time":52.00279865,"remaining_time":3.97437966},
{"learn":[0.4397167316],"iteration":929,"passed_time":52.05660775,"remaining_time":3.918239293},
{"learn":[0.4389847094],"iteration":930,"passed_time":52.11785513,"remaining_time":3.862655213},
{"learn":[0.4386852224],"iteration":931,"passed_time":52.17667397,"remaining_time":3.806881792},
{"learn":[0.4385425457],"iteration":932,"passed_time":52.23118828,"remaining_time":3.750792727},
{"learn":[0.4381054565],"iteration":933,"passed_time":52.28926555,"remaining_time":3.694958807},
{"learn":[0.4377011624],"iteration":934,"passed_time":52.34949292,"remaining_time":3.639269561},
{"learn":[0.4375277851],"iteration":935,"passed_time":52.40969016,"remaining_time":3.583568558},
{"learn":[0.4367722273],"iteration":936,"passed_time":52.46754248,"remaining_time":3.527700295},
{"learn":[0.4363954803],"iteration":937,"passed_time":52.52291142,"remaining_time":3.471663655},
{"learn":[0.4358990036],"iteration":938,"passed_time":52.58207789,"remaining_time":3.415875135},
{"learn":[0.4356173327],"iteration":939,"passed_time":52.6353923,"remaining_time":3.359705891},
{"learn":[0.4349928778],"iteration":940,"passed_time":52.69308422,"remaining_time":3.303817183},
{"learn":[0.4344275906],"iteration":941,"passed_time":52.74924986,"remaining_time":3.247830671},
{"learn":[0.4339370124],"iteration":942,"passed_time":52.80835562,"remaining_time":3.192021496},
{"learn":[0.4336537904],"iteration":943,"passed_time":52.86688477,"remaining_time":3.13617113},
{"learn":[0.4333094526],"iteration":944,"passed_time":52.9242237,"remaining_time":3.080245824},
{"learn":[0.4327469818],"iteration":945,"passed_time":52.98581454,"remaining_time":3.024560238},
{"learn":[0.4324643907],"iteration":946,"passed_time":53.04081485,"remaining_time":2.968493333},
{"learn":[0.431926898],"iteration":947,"passed_time":53.10347508,"remaining_time":2.912848844},
{"learn":[0.4314236734],"iteration":948,"passed_time":53.16114888,"remaining_time":2.856921594},
{"learn":[0.4309420548],"iteration":949,"passed_time":53.21658233,"remaining_time":2.800872754},
{"learn":[0.4302496731],"iteration":950,"passed_time":53.27204719,"remaining_time":2.744826827},
{"learn":[0.4299904872],"iteration":951,"passed_time":53.32485355,"remaining_time":2.688648078},
{"learn":[0.4298663729],"iteration":952,"passed_time":53.38209358,"remaining_time":2.632695066},
{"learn":[0.4292995405],"iteration":953,"passed_time":53.43703701,"remaining_time":2.576628619},
{"learn":[0.4285756244],"iteration":954,"passed_time":53.49663856,"remaining_time":2.520784016},
{"learn":[0.4281291369],"iteration":955,"passed_time":53.56011214,"remaining_time":2.465109764},
{"learn":[0.4274875311],"iteration":956,"passed_time":53.6179027,"remaining_time":2.409163862},
{"learn":[0.4270657738],"iteration":957,"passed_time":53.67386921,"remaining_time":2.353134141},
{"learn":[0.4265132153],"iteration":958,"passed_time":53.72795879,"remaining_time":2.297024307},
{"learn":[0.4258937743],"iteration":959,"passed_time":53.78407419,"remaining_time":2.241003091},
{"learn":[0.4251599865],"iteration":960,"passed_time":53.8411517,"remaining_time":2.185020725},
{"learn":[0.4249668092],"iteration":961,"passed_time":53.89773137,"remaining_time":2.129016416},
{"learn":[0.4247775752],"iteration":962,"passed_time":53.95298184,"remaining_time":2.072959842},
{"learn":[0.4242836023],"iteration":963,"passed_time":54.00913019,"remaining_time":2.016938472},
{"learn":[0.4236773159],"iteration":964,"passed_time":54.06391149,"remaining_time":1.960867256},
{"learn":[0.42332951],"iteration":965,"passed_time":54.12342242,"remaining_time":1.904965178},
{"learn":[0.4231750905],"iteration":966,"passed_time":54.17904444,"remaining_time":1.848922923},
{"learn":[0.4229258332],"iteration":967,"passed_time":54.23995967,"remaining_time":1.793056518},
{"learn":[0.4225152893],"iteration":968,"passed_time":54.29558217,"remaining_time":1.737010369},
{"learn":[0.4219318036],"iteration":969,"passed_time":54.35303614,"remaining_time":1.681021736},
{"learn":[0.4212846909],"iteration":970,"passed_time":54.41172236,"remaining_time":1.625066888},
{"learn":[0.4208496483],"iteration":971,"passed_time":54.46870141,"remaining_time":1.569057242},
{"learn":[0.4204233918],"iteration":972,"passed_time":54.52208745,"remaining_time":1.5129459},
{"learn":[0.4201691022],"iteration":973,"passed_time":54.57776573,"remaining_time":1.456901344},
{"learn":[0.419955201],"iteration":974,"passed_time":54.63995701,"remaining_time":1.401024539},
{"learn":[0.4194142265],"iteration":975,"passed_time":54.69544123,"remaining_time":1.344969866},
{"learn":[0.419213893],"iteration":976,"passed_time":54.74951684,"remaining_time":1.288883201},
{"learn":[0.4190593906],"iteration":977,"passed_time":54.80436713,"remaining_time":1.232818075},
{"learn":[0.418778394],"iteration":978,"passed_time":54.85823867,"remaining_time":1.176734435},
{"learn":[0.4184353671],"iteration":979,"passed_time":54.91597161,"remaining_time":1.120734114},
{"learn":[0.4179941164],"iteration":980,"passed_time":54.9710616,"remaining_time":1.064679073},
{"learn":[0.4176998196],"iteration":981,"passed_time":55.02616436,"remaining_time":1.008626231},
{"learn":[0.4172752904],"iteration":982,"passed_time":55.08092533,"remaining_time":0.9525694106},
{"learn":[0.4165951937],"iteration":983,"passed_time":55.13959925,"remaining_time":0.8965788496},
{"learn":[0.4160416485],"iteration":984,"passed_time":55.19580023,"remaining_time":0.8405451812},
{"learn":[0.4155591516],"iteration":985,"passed_time":55.25066889,"remaining_time":0.784492256},
{"learn":[0.4150563353],"iteration":986,"passed_time":55.30604694,"remaining_time":0.7284484399},
{"learn":[0.4147384632],"iteration":987,"passed_time":55.36229733,"remaining_time":0.6724165668},
{"learn":[0.4144630631],"iteration":988,"passed_time":55.42108465,"remaining_time":0.6164124683},
{"learn":[0.414006129],"iteration":989,"passed_time":55.47782053,"remaining_time":0.5603820255},
{"learn":[0.4137332593],"iteration":990,"passed_time":55.54226297,"remaining_time":0.5044201481},
{"learn":[0.4132233924],"iteration":991,"passed_time":55.60272977,"remaining_time":0.448409111},
{"learn":[0.4126684893],"iteration":992,"passed_time":55.65820478,"remaining_time":0.3923539108},
{"learn":[0.412150825],"iteration":993,"passed_time":55.71266888,"remaining_time":0.3362937759},
{"learn":[0.4116455369],"iteration":994,"passed_time":55.77011545,"remaining_time":0.2802518364},
{"learn":[0.4112654187],"iteration":995,"passed_time":55.82938479,"remaining_time":0.2242143967},
{"learn":[0.4109671204],"iteration":996,"passed_time":55.88347628,"remaining_time":0.1681548935},
{"learn":[0.4105757956],"iteration":997,"passed_time":55.94037328,"remaining_time":0.1121049565},
{"learn":[0.4100499393],"iteration":998,"passed_time":56.00259755,"remaining_time":0.05605865621},
{"learn":[0.4096802971],"iteration":999,"passed_time":56.05588488,"remaining_time":0}
]}